{
"nexml": {
"@about": "#study", 
"@generator": "Open Tree API", 
"@id": "study", 
"@nexml2json": "1.2.1", 
"@nexmljson": "http://purl.org/opentree/nexson", 
"@version": "0.9", 
"@xmlns": {
"$": "http://www.nexml.org/2009", 
"nex": "http://www.nexml.org/2009", 
"ot": "http://purl.org/opentree-terms#", 
"xhtml": "http://www.w3.org/1999/xhtml/vocab#", 
"xsd": "http://www.w3.org/2001/XMLSchema#", 
"xsi": "http://www.w3.org/2001/XMLSchema-instance"
}, 
"^ot:agents": {
"agent": [
{
"@description": "Open Tree NexSON validation", 
"@id": "peyotl-validator", 
"@name": "api.opentreeoflife.org/validate", 
"@url": "https://github.com/OpenTreeOfLife/peyotl", 
"@version": "0.0.4a", 
"invocation": {
"commandLine": [], 
"otherProperty": [
{
"name": "pythonVersion", 
"value": "2.7.16"
}, 
{
"name": "pythonImplementation", 
"value": "CPython"
}
]
}
}, 
{
"@description": "Web-based interface for submitting, editing, and reviewing studies in the Open Tree of Life project.", 
"@id": "opentree-curation-webapp", 
"@name": "OpenTree curation webapp", 
"@url": "https://github.com/OpenTreeOfLife/opentree", 
"@version": "0.0.0"
}
]
}, 
"^ot:annotationEvents": {
"annotation": [
{
"@dateCreated": "2022-05-27T15:24:04.752Z", 
"@description": "Aids for mapping study OTUs to OTT taxa", 
"@id": "otu-mapping-hints", 
"@passedChecks": true, 
"@preserve": true, 
"@wasAssociatedWithAgentId": "opentree-curation-webapp", 
"message": [
{
"@code": "OTU_MAPPING_HINTS", 
"@humanMessageType": "NONE", 
"@severity": "INFO", 
"data": {
"autoAcceptExactMatches": true, 
"searchContext": {
"$": "All life"
}, 
"substitutions": {
"substitution": [
{
"@active": false, 
"@valid": true, 
"new": {
"$": ""
}, 
"old": {
"$": ""
}
}
]
}, 
"useFuzzyMatching": false
}, 
"refersTo": {
"@top": {
"$": "meta"
}
}
}
]
}, 
{
"@dateCreated": "2022-05-27T15:24:04.752Z", 
"@description": "Describes external namesets merged into this study", 
"@id": "merged-namesets-metadata", 
"@passedChecks": true, 
"@preserve": true, 
"@wasAssociatedWithAgentId": "opentree-curation-webapp", 
"message": [
{
"@code": "MERGED_NAMESET_INFO", 
"@humanMessageType": "NONE", 
"@severity": "INFO", 
"data": {
"namesets": {
"nameset": []
}
}, 
"refersTo": {
"@top": {
"$": "meta"
}
}
}
]
}, 
{
"@dateCreated": "2022-05-27T15:24:04.752Z", 
"@description": "Describes supporting data files for this study", 
"@id": "supporting-files-metadata", 
"@passedChecks": true, 
"@preserve": true, 
"@wasAssociatedWithAgentId": "opentree-curation-webapp", 
"message": [
{
"@code": "SUPPORTING_FILE_INFO", 
"@humanMessageType": "NONE", 
"@severity": "INFO", 
"data": {
"@movedToPermanentArchive": false, 
"files": {
"file": [
{
"@filename": "mcc_obs_v2", 
"@size": 64707, 
"@type": "", 
"@url": "/curator/supporting_files/download/supporting_files.doc.8c2e6ed7894f4e84.6d63635f6f62735f7632.txt", 
"description": {
"$": "Nexus"
}, 
"sourceForTree": []
}, 
{
"@filename": "mcc_obs_v2", 
"@size": 64707, 
"@type": "nexus", 
"@url": "/curator/download/supporting_files.doc.9c495332cb317230.6d63635f6f62735f7632.txt", 
"description": {
"$": "Source data for tree(s) 'tree1'"
}, 
"sourceForTree": [
{
"$": "tree1"
}
]
}
]
}
}, 
"refersTo": {
"@top": {
"$": "meta"
}
}
}
]
}
]
}, 
"^ot:candidateTreeForSynthesis": [], 
"^ot:comment": "", 
"^ot:curatorName": [
"drmatute"
], 
"^ot:dataDeposit": {
"@href": ""
}, 
"^ot:focalCladeOTTTaxonName": "", 
"^ot:otusElementOrder": [
"otus1"
], 
"^ot:studyId": "ot_2093", 
"^ot:studyPublication": {
"@href": ""
}, 
"^ot:studyPublicationReference": "Climatic niche conservatism in a clade of disease vectors (Diptera: Phlebotominae). D'Agostino et al. 2022. Evolution", 
"^ot:studyYear": 2022, 
"^ot:tag": [], 
"^ot:treesElementOrder": [
"trees1"
], 
"^xhtml:license": {
"@href": "http://creativecommons.org/publicdomain/zero/1.0/", 
"@name": "CC0"
}, 
"otusById": {
"otus1": {
"otuById": {
"otu1": {
"^ot:originalLabel": "Ae albopictus", 
"^ot:ottId": 793181, 
"^ot:ottTaxonName": "Aedes albopictus"
}, 
"otu10": {
"^ot:originalLabel": "Ev edwardsi", 
"^ot:ottId": 4456806, 
"^ot:ottTaxonName": "Evandromyia edwardsi"
}, 
"otu11": {
"^ot:originalLabel": "Ev infraspinosa", 
"^ot:ottId": 4456855, 
"^ot:ottTaxonName": "Evandromyia infraspinosa"
}, 
"otu12": {
"^ot:originalLabel": "Ev lenti", 
"^ot:ottId": 5960260, 
"^ot:ottTaxonName": "Evandromyia lenti"
}, 
"otu13": {
"^ot:originalLabel": "Ev termitophila", 
"^ot:ottId": 5960263, 
"^ot:ottTaxonName": "Evandromyia termitophila"
}, 
"otu14": {
"^ot:originalLabel": "Lu carpenteri", 
"^ot:ottId": 748261, 
"^ot:ottTaxonName": "Psathyromyia carpenteri"
}, 
"otu15": {
"^ot:originalLabel": "Lu cayennensis", 
"^ot:ottId": 655611, 
"^ot:ottTaxonName": "Micropygomyia cayennensis"
}, 
"otu16": {
"^ot:originalLabel": "Lu columbiana", 
"^ot:ottId": 889764, 
"^ot:ottTaxonName": "Lutzomyia columbiana"
}, 
"otu17": {
"^ot:originalLabel": "Lu cruciata", 
"^ot:ottId": 4456914, 
"^ot:ottTaxonName": "Lutzomyia cruciata"
}, 
"otu18": {
"^ot:originalLabel": "Lu cruzi", 
"^ot:ottId": 370231, 
"^ot:ottTaxonName": "Lutzomyia cruzi"
}, 
"otu19": {
"^ot:originalLabel": "Lu deleoni", 
"^ot:ottId": 4456943, 
"^ot:ottTaxonName": "Lutzomyia deleoni"
}, 
"otu2": {
"^ot:originalLabel": "Aedes aegypti", 
"^ot:ottId": 269666, 
"^ot:ottTaxonName": "Aedes aegypti"
}, 
"otu20": {
"^ot:originalLabel": "Lu evansi", 
"^ot:ottId": 1055673, 
"^ot:ottTaxonName": "Lutzomyia evansi"
}, 
"otu21": {
"^ot:originalLabel": "Lu gomezi", 
"^ot:ottId": 285584, 
"^ot:ottTaxonName": "Lutzomyia gomezi"
}, 
"otu22": {
"^ot:originalLabel": "Lu hartmanni", 
"^ot:ottId": 394436, 
"^ot:ottTaxonName": "Lutzomyia hartmanni"
}, 
"otu23": {
"^ot:originalLabel": "Lu longipalpis", 
"^ot:ottId": 555810, 
"^ot:ottTaxonName": "Lutzomyia longipalpis"
}, 
"otu24": {
"^ot:originalLabel": "Lu migonei", 
"^ot:ottId": 266172, 
"^ot:ottTaxonName": "Migonemyia migonei"
}, 
"otu25": {
"^ot:originalLabel": "Lu olmeca", 
"^ot:ottId": 748266, 
"^ot:ottTaxonName": "Bichromomyia olmeca"
}, 
"otu26": {
"^ot:originalLabel": "Lu ovallesi", 
"^ot:ottId": 939578, 
"^ot:ottTaxonName": "Lutzomyia ovallesi"
}, 
"otu27": {
"^ot:originalLabel": "Lu shannoni", 
"^ot:ottId": 144502, 
"^ot:ottTaxonName": "Psathyromyia shannoni"
}, 
"otu28": {
"^ot:originalLabel": "Lu trapidoi", 
"^ot:ottId": 22235, 
"^ot:ottTaxonName": "Nyssomyia trapidoi"
}, 
"otu29": {
"^ot:originalLabel": "Lu trinidadensis", 
"^ot:ottId": 910838, 
"^ot:ottTaxonName": "Lutzomyia trinidadensis"
}, 
"otu3": {
"^ot:originalLabel": "Br cunhai", 
"^ot:ottId": 4457072, 
"^ot:ottTaxonName": "Brumptomyia cunhai"
}, 
"otu30": {
"^ot:originalLabel": "Lu verrucarum", 
"^ot:ottId": 1041848, 
"^ot:ottTaxonName": "Lutzomyia verrucarum"
}, 
"otu31": {
"^ot:originalLabel": "Lu youngi", 
"^ot:ottId": 266171, 
"^ot:ottTaxonName": "Lutzomyia youngi"
}, 
"otu32": {
"^ot:originalLabel": "Lutzomyia renei", 
"^ot:ottId": 707307, 
"^ot:ottTaxonName": "Lutzomyia renei"
}, 
"otu33": {
"^ot:originalLabel": "Peri blandula", 
"^ot:ottId": 594543, 
"^ot:ottTaxonName": "Pericoma blandula"
}, 
"otu34": {
"^ot:originalLabel": "Peri rivularis", 
"^ot:ottId": 464049, 
"^ot:ottTaxonName": "Pericoma rivularis"
}, 
"otu35": {
"^ot:originalLabel": "Peri trifasciata", 
"^ot:ottId": 4455545, 
"^ot:ottTaxonName": "Pericoma trifasciata"
}, 
"otu36": {
"^ot:originalLabel": "Ph argentipes", 
"^ot:ottId": 3670, 
"^ot:ottTaxonName": "Phlebotomus argentipes"
}, 
"otu37": {
"^ot:originalLabel": "Ph duboscqi", 
"^ot:ottId": 631414, 
"^ot:ottTaxonName": "Phlebotomus duboscqi"
}, 
"otu38": {
"^ot:originalLabel": "Ph mascittii", 
"^ot:ottId": 1064019, 
"^ot:ottTaxonName": "Phlebotomus mascittii"
}, 
"otu39": {
"^ot:originalLabel": "Ph neglectus", 
"^ot:ottId": 840812, 
"^ot:ottTaxonName": "Phlebotomus neglectus"
}, 
"otu4": {
"^ot:originalLabel": "Br galindoi", 
"^ot:ottId": 748255, 
"^ot:ottTaxonName": "Brumptomyia galindoi"
}, 
"otu40": {
"^ot:originalLabel": "Ph papatasi", 
"^ot:ottId": 1008039, 
"^ot:ottTaxonName": "Phlebotomus papatasi"
}, 
"otu41": {
"^ot:originalLabel": "Ph perfiliewi", 
"^ot:ottId": 922912, 
"^ot:ottTaxonName": "Phlebotomus perfiliewi"
}, 
"otu42": {
"^ot:originalLabel": "Ph perniciosus", 
"^ot:ottId": 744761, 
"^ot:ottTaxonName": "Phlebotomus perniciosus"
}, 
"otu43": {
"^ot:originalLabel": "Ph sergenti", 
"^ot:ottId": 639576, 
"^ot:ottTaxonName": "Phlebotomus sergenti"
}, 
"otu44": {
"^ot:originalLabel": "Ph simici", 
"^ot:ottId": 576316, 
"^ot:ottTaxonName": "Phlebotomus simici"
}, 
"otu45": {
"^ot:originalLabel": "Ph similis", 
"^ot:ottId": 775747, 
"^ot:ottTaxonName": "Phlebotomus similis"
}, 
"otu46": {
"^ot:originalLabel": "Ph stantoni", 
"^ot:ottId": 4457146, 
"^ot:ottTaxonName": "Phlebotomus stantoni"
}, 
"otu47": {
"^ot:originalLabel": "Ph tobbi", 
"^ot:ottId": 106240, 
"^ot:ottTaxonName": "Phlebotomus tobbi"
}, 
"otu48": {
"^ot:originalLabel": "Phil humeralis", 
"^ot:ottId": 4455399, 
"^ot:ottTaxonName": "Philosepedon humeralis"
}, 
"otu49": {
"^ot:originalLabel": "Pi fischeri", 
"^ot:ottId": 1080850, 
"^ot:ottTaxonName": "Pintomyia fischeri"
}, 
"otu5": {
"^ot:originalLabel": "Br hamata", 
"^ot:ottId": 202308, 
"^ot:ottTaxonName": "Brumptomyia hamata"
}, 
"otu50": {
"^ot:originalLabel": "Ps carrerai", 
"^ot:ottId": 748259, 
"^ot:ottTaxonName": "Psychodopygus carrerai"
}, 
"otu51": {
"^ot:originalLabel": "Ps chagasi", 
"^ot:ottId": 7366213, 
"^ot:ottTaxonName": "Psychodopygus chagasi"
}, 
"otu52": {
"^ot:originalLabel": "Ps davisi", 
"^ot:ottId": 5823593, 
"^ot:ottTaxonName": "Psychodopygus davisi"
}, 
"otu53": {
"^ot:originalLabel": "Ps geniculatus", 
"^ot:ottId": 1088135, 
"^ot:ottTaxonName": "Psychodopygus geniculatus"
}, 
"otu54": {
"^ot:originalLabel": "Ps hirsutus", 
"^ot:ottId": 5823591, 
"^ot:ottTaxonName": "Psychodopygus hirsutus"
}, 
"otu55": {
"^ot:originalLabel": "Ps panamensis", 
"^ot:ottId": 910828, 
"^ot:ottTaxonName": "Psychodopygus panamensis"
}, 
"otu56": {
"^ot:originalLabel": "Ps squamiventris", 
"^ot:ottId": 4456850, 
"^ot:ottTaxonName": "Psychodopygus squamiventris"
}, 
"otu57": {
"^ot:originalLabel": "Psa aragaoi", 
"^ot:ottId": 4456978, 
"^ot:ottTaxonName": "Psathyromyia aragaoi"
}, 
"otu58": {
"^ot:originalLabel": "Psa lutziana", 
"^ot:ottId": 4456898, 
"^ot:ottTaxonName": "Psathyromyia lutziana"
}, 
"otu59": {
"^ot:originalLabel": "Psyc albipennis", 
"^ot:ottId": 736525, 
"^ot:ottTaxonName": "Psychoda albipennis"
}, 
"otu6": {
"^ot:originalLabel": "Br nitzulescui", 
"^ot:ottId": 4457085, 
"^ot:ottTaxonName": "Brumptomyia nitzulescui"
}, 
"otu60": {
"^ot:originalLabel": "Psyc alternata", 
"^ot:ottId": 756199, 
"^ot:ottTaxonName": "Psychoda alternata"
}, 
"otu61": {
"^ot:originalLabel": "Psyc alticola", 
"^ot:ottId": 4455891, 
"^ot:ottTaxonName": "Psychoda alticola"
}, 
"otu62": {
"^ot:originalLabel": "Psyc cinerea", 
"^ot:ottId": 555808, 
"^ot:ottTaxonName": "Psychoda cinerea"
}, 
"otu63": {
"^ot:originalLabel": "Psyc erminea", 
"^ot:ottId": 295153, 
"^ot:ottTaxonName": "Psychoda erminea"
}, 
"otu64": {
"^ot:originalLabel": "Psyc gemina", 
"^ot:ottId": 596349, 
"^ot:ottTaxonName": "Psychoda gemina"
}, 
"otu65": {
"^ot:originalLabel": "Psyc grisescens", 
"^ot:ottId": 702481, 
"^ot:ottTaxonName": "Psychoda grisescens"
}, 
"otu66": {
"^ot:originalLabel": "Psyc lobata", 
"^ot:ottId": 736523, 
"^ot:ottTaxonName": "Psychoda lobata"
}, 
"otu67": {
"^ot:originalLabel": "Psyc phalaenoides", 
"^ot:ottId": 702478, 
"^ot:ottTaxonName": "Psychoda phalaenoides"
}, 
"otu68": {
"^ot:originalLabel": "Psyc setigera", 
"^ot:ottId": 802891, 
"^ot:ottTaxonName": "Psychoda setigera"
}, 
"otu69": {
"^ot:originalLabel": "Psyc sigma", 
"^ot:ottId": 4455922, 
"^ot:ottTaxonName": "Psychoda sigma"
}, 
"otu7": {
"^ot:originalLabel": "Br travassosi", 
"^ot:ottId": 4457076, 
"^ot:ottTaxonName": "Brumptomyia travassosi"
}, 
"otu70": {
"^ot:originalLabel": "Psyc trinodulosa", 
"^ot:ottId": 4456063, 
"^ot:ottTaxonName": "Psychoda trinodulosa"
}, 
"otu71": {
"^ot:originalLabel": "Satc trivialis", 
"^ot:ottId": 329116, 
"^ot:ottTaxonName": "Satchelliella trivialis"
}, 
"otu72": {
"^ot:originalLabel": "Se africana", 
"^ot:ottId": 4457191, 
"^ot:ottTaxonName": "Sergentomyia africana"
}, 
"otu73": {
"^ot:originalLabel": "Se anodontis", 
"^ot:ottId": 4457195, 
"^ot:ottTaxonName": "Sergentomyia anodontis"
}, 
"otu74": {
"^ot:originalLabel": "Se antennata", 
"^ot:ottId": 170969, 
"^ot:ottTaxonName": "Sergentomyia antennata"
}, 
"otu75": {
"^ot:originalLabel": "Se bedfordi", 
"^ot:ottId": 4457188, 
"^ot:ottTaxonName": "Sergentomyia bedfordi"
}, 
"otu76": {
"^ot:originalLabel": "Se clydei", 
"^ot:ottId": 201494, 
"^ot:ottTaxonName": "Sergentomyia clydei"
}, 
"otu77": {
"^ot:originalLabel": "Se ingrami", 
"^ot:ottId": 4457214, 
"^ot:ottTaxonName": "Sergentomyia ingrami"
}, 
"otu78": {
"^ot:originalLabel": "Se minuta", 
"^ot:ottId": 922909, 
"^ot:ottTaxonName": "Sergentomyia minuta"
}, 
"otu79": {
"^ot:originalLabel": "Se schwetzi", 
"^ot:ottId": 201496, 
"^ot:ottTaxonName": "Sergentomyia schwetzi"
}, 
"otu8": {
"^ot:originalLabel": "Clyto ocellaris", 
"^ot:ottId": 143037, 
"^ot:ottTaxonName": "Clytocerus ocellaris"
}, 
"otu80": {
"^ot:originalLabel": "Telm advenus", 
"^ot:ottId": 378346, 
"^ot:ottTaxonName": "Telmatoscopus advenus"
}, 
"otu81": {
"^ot:originalLabel": "Telm albipunctatus", 
"^ot:ottId": 883749, 
"^ot:ottTaxonName": "Telmatoscopus albipunctatus"
}, 
"otu9": {
"^ot:originalLabel": "Ev cortelezzii", 
"^ot:ottId": 7366039, 
"^ot:ottTaxonName": "Evandromyia cortelezzii"
}
}
}
}, 
"treesById": {
"trees1": {
"@otus": "otus1", 
"^ot:treeElementOrder": [
"tree1"
], 
"treeById": {
"tree1": {
"@label": "TREE1", 
"@xsi:type": "nex:FloatTree", 
"^ot:branchLengthDescription": "", 
"^ot:branchLengthMode": "ot:substitutionCount", 
"^ot:curatedType": "Bayesian inference ", 
"^ot:inGroupClade": "node2", 
"^ot:nodeLabelMode": "", 
"^ot:nodeLabelTimeUnit": "", 
"^ot:outGroupEdge": "", 
"^ot:reasonsToExcludeFromSynthesis": [], 
"^ot:rootNodeId": "node1", 
"^ot:specifiedRoot": "node1", 
"^ot:tag": [], 
"^ot:unrootedTree": false, 
"edgeBySourceId": {
"node1": {
"edge1": {
"@length": 0.03729, 
"@source": "node1", 
"@target": "node2"
}, 
"edge158": {
"@length": 0.153731, 
"@source": "node1", 
"@target": "node159"
}
}, 
"node100": {
"edge100": {
"@length": 0.050097, 
"@source": "node100", 
"@target": "node101"
}, 
"edge101": {
"@length": 0.050097, 
"@source": "node100", 
"@target": "node102"
}
}, 
"node103": {
"edge103": {
"@length": 0.037099, 
"@source": "node103", 
"@target": "node104"
}, 
"edge104": {
"@length": 0.030289, 
"@source": "node103", 
"@target": "node105"
}
}, 
"node105": {
"edge105": {
"@length": 0.00681, 
"@source": "node105", 
"@target": "node106"
}, 
"edge106": {
"@length": 0.00681, 
"@source": "node105", 
"@target": "node107"
}
}, 
"node108": {
"edge108": {
"@length": 0.070451, 
"@source": "node108", 
"@target": "node109"
}, 
"edge109": {
"@length": 0.070451, 
"@source": "node108", 
"@target": "node110"
}
}, 
"node11": {
"edge11": {
"@length": 0.017292, 
"@source": "node11", 
"@target": "node12"
}, 
"edge14": {
"@length": 0.068168, 
"@source": "node11", 
"@target": "node15"
}
}, 
"node111": {
"edge111": {
"@length": 0.014174, 
"@source": "node111", 
"@target": "node112"
}, 
"edge118": {
"@length": 0.013986, 
"@source": "node111", 
"@target": "node119"
}
}, 
"node112": {
"edge112": {
"@length": 0.09482, 
"@source": "node112", 
"@target": "node113"
}, 
"edge113": {
"@length": 0.032313, 
"@source": "node112", 
"@target": "node114"
}
}, 
"node114": {
"edge114": {
"@length": 0.052319, 
"@source": "node114", 
"@target": "node115"
}, 
"edge117": {
"@length": 0.062507, 
"@source": "node114", 
"@target": "node118"
}
}, 
"node115": {
"edge115": {
"@length": 0.010188, 
"@source": "node115", 
"@target": "node116"
}, 
"edge116": {
"@length": 0.010188, 
"@source": "node115", 
"@target": "node117"
}
}, 
"node119": {
"edge119": {
"@length": 0.018973, 
"@source": "node119", 
"@target": "node120"
}, 
"edge126": {
"@length": 0.01461, 
"@source": "node119", 
"@target": "node127"
}
}, 
"node12": {
"edge12": {
"@length": 0.050877, 
"@source": "node12", 
"@target": "node13"
}, 
"edge13": {
"@length": 0.050877, 
"@source": "node12", 
"@target": "node14"
}
}, 
"node120": {
"edge120": {
"@length": 0.036244, 
"@source": "node120", 
"@target": "node121"
}, 
"edge123": {
"@length": 0.017726, 
"@source": "node120", 
"@target": "node124"
}
}, 
"node121": {
"edge121": {
"@length": 0.039791, 
"@source": "node121", 
"@target": "node122"
}, 
"edge122": {
"@length": 0.039791, 
"@source": "node121", 
"@target": "node123"
}
}, 
"node124": {
"edge124": {
"@length": 0.05831, 
"@source": "node124", 
"@target": "node125"
}, 
"edge125": {
"@length": 0.05831, 
"@source": "node124", 
"@target": "node126"
}
}, 
"node127": {
"edge127": {
"@length": 0.080399, 
"@source": "node127", 
"@target": "node128"
}, 
"edge128": {
"@length": 0.012652, 
"@source": "node127", 
"@target": "node129"
}
}, 
"node129": {
"edge129": {
"@length": 0.015243, 
"@source": "node129", 
"@target": "node130"
}, 
"edge132": {
"@length": 0.067747, 
"@source": "node129", 
"@target": "node133"
}
}, 
"node130": {
"edge130": {
"@length": 0.052503, 
"@source": "node130", 
"@target": "node131"
}, 
"edge131": {
"@length": 0.052503, 
"@source": "node130", 
"@target": "node132"
}
}, 
"node134": {
"edge134": {
"@length": 0.035149, 
"@source": "node134", 
"@target": "node135"
}, 
"edge149": {
"@length": 0.044603, 
"@source": "node134", 
"@target": "node150"
}
}, 
"node135": {
"edge135": {
"@length": 0.014304, 
"@source": "node135", 
"@target": "node136"
}, 
"edge144": {
"@length": 0.027397, 
"@source": "node135", 
"@target": "node145"
}
}, 
"node136": {
"edge136": {
"@length": 0.081516, 
"@source": "node136", 
"@target": "node137"
}, 
"edge137": {
"@length": 0.025085, 
"@source": "node136", 
"@target": "node138"
}
}, 
"node138": {
"edge138": {
"@length": 0.056431, 
"@source": "node138", 
"@target": "node139"
}, 
"edge139": {
"@length": 0.013397, 
"@source": "node138", 
"@target": "node140"
}
}, 
"node140": {
"edge140": {
"@length": 0.010651, 
"@source": "node140", 
"@target": "node141"
}, 
"edge143": {
"@length": 0.043034, 
"@source": "node140", 
"@target": "node144"
}
}, 
"node141": {
"edge141": {
"@length": 0.032383, 
"@source": "node141", 
"@target": "node142"
}, 
"edge142": {
"@length": 0.032383, 
"@source": "node141", 
"@target": "node143"
}
}, 
"node145": {
"edge145": {
"@length": 0.018911, 
"@source": "node145", 
"@target": "node146"
}, 
"edge148": {
"@length": 0.068423, 
"@source": "node145", 
"@target": "node149"
}
}, 
"node146": {
"edge146": {
"@length": 0.049512, 
"@source": "node146", 
"@target": "node147"
}, 
"edge147": {
"@length": 0.049512, 
"@source": "node146", 
"@target": "node148"
}
}, 
"node150": {
"edge150": {
"@length": 0.022515, 
"@source": "node150", 
"@target": "node151"
}, 
"edge157": {
"@length": 0.086366, 
"@source": "node150", 
"@target": "node158"
}
}, 
"node151": {
"edge151": {
"@length": 0.006875, 
"@source": "node151", 
"@target": "node152"
}, 
"edge156": {
"@length": 0.063851, 
"@source": "node151", 
"@target": "node157"
}
}, 
"node152": {
"edge152": {
"@length": 0.043602, 
"@source": "node152", 
"@target": "node153"
}, 
"edge155": {
"@length": 0.056976, 
"@source": "node152", 
"@target": "node156"
}
}, 
"node153": {
"edge153": {
"@length": 0.013374, 
"@source": "node153", 
"@target": "node154"
}, 
"edge154": {
"@length": 0.013374, 
"@source": "node153", 
"@target": "node155"
}
}, 
"node159": {
"edge159": {
"@length": 0.093365, 
"@source": "node159", 
"@target": "node160"
}, 
"edge160": {
"@length": 0.093365, 
"@source": "node159", 
"@target": "node161"
}
}, 
"node16": {
"edge16": {
"@length": 0.073386, 
"@source": "node16", 
"@target": "node17"
}, 
"edge17": {
"@length": 0.073386, 
"@source": "node16", 
"@target": "node18"
}
}, 
"node19": {
"edge19": {
"@length": 0.016379, 
"@source": "node19", 
"@target": "node20"
}, 
"edge26": {
"@length": 0.012403, 
"@source": "node19", 
"@target": "node27"
}
}, 
"node2": {
"edge2": {
"@length": 0.079011, 
"@source": "node2", 
"@target": "node3"
}, 
"edge41": {
"@length": 0.056068, 
"@source": "node2", 
"@target": "node42"
}
}, 
"node20": {
"edge20": {
"@length": 0.014946, 
"@source": "node20", 
"@target": "node21"
}, 
"edge23": {
"@length": 0.020792, 
"@source": "node20", 
"@target": "node24"
}
}, 
"node21": {
"edge21": {
"@length": 0.065815, 
"@source": "node21", 
"@target": "node22"
}, 
"edge22": {
"@length": 0.065815, 
"@source": "node21", 
"@target": "node23"
}
}, 
"node24": {
"edge24": {
"@length": 0.059969, 
"@source": "node24", 
"@target": "node25"
}, 
"edge25": {
"@length": 0.059969, 
"@source": "node24", 
"@target": "node26"
}
}, 
"node27": {
"edge27": {
"@length": 0.01714, 
"@source": "node27", 
"@target": "node28"
}, 
"edge30": {
"@length": 0.011999, 
"@source": "node27", 
"@target": "node31"
}
}, 
"node28": {
"edge28": {
"@length": 0.067596, 
"@source": "node28", 
"@target": "node29"
}, 
"edge29": {
"@length": 0.067596, 
"@source": "node28", 
"@target": "node30"
}
}, 
"node3": {
"edge18": {
"@length": 0.033656, 
"@source": "node3", 
"@target": "node19"
}, 
"edge3": {
"@length": 0.019659, 
"@source": "node3", 
"@target": "node4"
}
}, 
"node31": {
"edge31": {
"@length": 0.009628, 
"@source": "node31", 
"@target": "node32"
}, 
"edge38": {
"@length": 0.016972, 
"@source": "node31", 
"@target": "node39"
}
}, 
"node32": {
"edge32": {
"@length": 0.019925, 
"@source": "node32", 
"@target": "node33"
}, 
"edge35": {
"@length": 0.01577, 
"@source": "node32", 
"@target": "node36"
}
}, 
"node33": {
"edge33": {
"@length": 0.043185, 
"@source": "node33", 
"@target": "node34"
}, 
"edge34": {
"@length": 0.043185, 
"@source": "node33", 
"@target": "node35"
}
}, 
"node36": {
"edge36": {
"@length": 0.04734, 
"@source": "node36", 
"@target": "node37"
}, 
"edge37": {
"@length": 0.04734, 
"@source": "node36", 
"@target": "node38"
}
}, 
"node39": {
"edge39": {
"@length": 0.055766, 
"@source": "node39", 
"@target": "node40"
}, 
"edge40": {
"@length": 0.055766, 
"@source": "node39", 
"@target": "node41"
}
}, 
"node4": {
"edge4": {
"@length": 0.111138, 
"@source": "node4", 
"@target": "node5"
}, 
"edge5": {
"@length": 0.011937, 
"@source": "node4", 
"@target": "node6"
}
}, 
"node42": {
"edge133": {
"@length": 0.02277, 
"@source": "node42", 
"@target": "node134"
}, 
"edge42": {
"@length": 0.020482, 
"@source": "node42", 
"@target": "node43"
}
}, 
"node43": {
"edge110": {
"@length": 0.024262, 
"@source": "node43", 
"@target": "node111"
}, 
"edge43": {
"@length": 0.029257, 
"@source": "node43", 
"@target": "node44"
}
}, 
"node44": {
"edge107": {
"@length": 0.033549, 
"@source": "node44", 
"@target": "node108"
}, 
"edge44": {
"@length": 0.011179, 
"@source": "node44", 
"@target": "node45"
}
}, 
"node45": {
"edge45": {
"@length": 0.014248, 
"@source": "node45", 
"@target": "node46"
}, 
"edge78": {
"@length": 0.017957, 
"@source": "node45", 
"@target": "node79"
}
}, 
"node46": {
"edge46": {
"@length": 0.01208, 
"@source": "node46", 
"@target": "node47"
}, 
"edge51": {
"@length": 0.008694, 
"@source": "node46", 
"@target": "node52"
}
}, 
"node47": {
"edge47": {
"@length": 0.066492, 
"@source": "node47", 
"@target": "node48"
}, 
"edge48": {
"@length": 0.04055, 
"@source": "node47", 
"@target": "node49"
}
}, 
"node49": {
"edge49": {
"@length": 0.025941, 
"@source": "node49", 
"@target": "node50"
}, 
"edge50": {
"@length": 0.025941, 
"@source": "node49", 
"@target": "node51"
}
}, 
"node52": {
"edge52": {
"@length": 0.00652, 
"@source": "node52", 
"@target": "node53"
}, 
"edge71": {
"@length": 0.011044, 
"@source": "node52", 
"@target": "node72"
}
}, 
"node53": {
"edge53": {
"@length": 0.012032, 
"@source": "node53", 
"@target": "node54"
}, 
"edge56": {
"@length": 0.00563, 
"@source": "node53", 
"@target": "node57"
}
}, 
"node54": {
"edge54": {
"@length": 0.051326, 
"@source": "node54", 
"@target": "node55"
}, 
"edge55": {
"@length": 0.051326, 
"@source": "node54", 
"@target": "node56"
}
}, 
"node57": {
"edge57": {
"@length": 0.009306, 
"@source": "node57", 
"@target": "node58"
}, 
"edge60": {
"@length": 0.006639, 
"@source": "node57", 
"@target": "node61"
}
}, 
"node58": {
"edge58": {
"@length": 0.048423, 
"@source": "node58", 
"@target": "node59"
}, 
"edge59": {
"@length": 0.048423, 
"@source": "node58", 
"@target": "node60"
}
}, 
"node6": {
"edge15": {
"@length": 0.025814, 
"@source": "node6", 
"@target": "node16"
}, 
"edge6": {
"@length": 0.009444, 
"@source": "node6", 
"@target": "node7"
}
}, 
"node61": {
"edge61": {
"@length": 0.012061, 
"@source": "node61", 
"@target": "node62"
}, 
"edge64": {
"@length": 0.010303, 
"@source": "node61", 
"@target": "node65"
}
}, 
"node62": {
"edge62": {
"@length": 0.039028, 
"@source": "node62", 
"@target": "node63"
}, 
"edge63": {
"@length": 0.039028, 
"@source": "node62", 
"@target": "node64"
}
}, 
"node65": {
"edge65": {
"@length": 0.040786, 
"@source": "node65", 
"@target": "node66"
}, 
"edge66": {
"@length": 0.020603, 
"@source": "node65", 
"@target": "node67"
}
}, 
"node67": {
"edge67": {
"@length": 0.00703, 
"@source": "node67", 
"@target": "node68"
}, 
"edge70": {
"@length": 0.020183, 
"@source": "node67", 
"@target": "node71"
}
}, 
"node68": {
"edge68": {
"@length": 0.013153, 
"@source": "node68", 
"@target": "node69"
}, 
"edge69": {
"@length": 0.013153, 
"@source": "node68", 
"@target": "node70"
}
}, 
"node7": {
"edge10": {
"@length": 0.021588, 
"@source": "node7", 
"@target": "node11"
}, 
"edge7": {
"@length": 0.018563, 
"@source": "node7", 
"@target": "node8"
}
}, 
"node72": {
"edge72": {
"@length": 0.017152, 
"@source": "node72", 
"@target": "node73"
}, 
"edge75": {
"@length": 0.010226, 
"@source": "node72", 
"@target": "node76"
}
}, 
"node73": {
"edge73": {
"@length": 0.041682, 
"@source": "node73", 
"@target": "node74"
}, 
"edge74": {
"@length": 0.041682, 
"@source": "node73", 
"@target": "node75"
}
}, 
"node76": {
"edge76": {
"@length": 0.048609, 
"@source": "node76", 
"@target": "node77"
}, 
"edge77": {
"@length": 0.048609, 
"@source": "node76", 
"@target": "node78"
}
}, 
"node79": {
"edge102": {
"@length": 0.037764, 
"@source": "node79", 
"@target": "node103"
}, 
"edge79": {
"@length": 0.009229, 
"@source": "node79", 
"@target": "node80"
}
}, 
"node8": {
"edge8": {
"@length": 0.071193, 
"@source": "node8", 
"@target": "node9"
}, 
"edge9": {
"@length": 0.071193, 
"@source": "node8", 
"@target": "node10"
}
}, 
"node80": {
"edge80": {
"@length": 0.008296, 
"@source": "node80", 
"@target": "node81"
}, 
"edge99": {
"@length": 0.015537, 
"@source": "node80", 
"@target": "node100"
}
}, 
"node81": {
"edge81": {
"@length": 0.011495, 
"@source": "node81", 
"@target": "node82"
}, 
"edge88": {
"@length": 0.0064, 
"@source": "node81", 
"@target": "node89"
}
}, 
"node82": {
"edge82": {
"@length": 0.014982, 
"@source": "node82", 
"@target": "node83"
}, 
"edge87": {
"@length": 0.045842, 
"@source": "node82", 
"@target": "node88"
}
}, 
"node83": {
"edge83": {
"@length": 0.022656, 
"@source": "node83", 
"@target": "node84"
}, 
"edge86": {
"@length": 0.030861, 
"@source": "node83", 
"@target": "node87"
}
}, 
"node84": {
"edge84": {
"@length": 0.008205, 
"@source": "node84", 
"@target": "node85"
}, 
"edge85": {
"@length": 0.008205, 
"@source": "node84", 
"@target": "node86"
}
}, 
"node89": {
"edge89": {
"@length": 0.007075, 
"@source": "node89", 
"@target": "node90"
}, 
"edge98": {
"@length": 0.050938, 
"@source": "node89", 
"@target": "node99"
}
}, 
"node90": {
"edge90": {
"@length": 0.0044, 
"@source": "node90", 
"@target": "node91"
}, 
"edge93": {
"@length": 0.019563, 
"@source": "node90", 
"@target": "node94"
}
}, 
"node91": {
"edge91": {
"@length": 0.039462, 
"@source": "node91", 
"@target": "node92"
}, 
"edge92": {
"@length": 0.039462, 
"@source": "node91", 
"@target": "node93"
}
}, 
"node94": {
"edge94": {
"@length": 0.0243, 
"@source": "node94", 
"@target": "node95"
}, 
"edge95": {
"@length": 0.014049, 
"@source": "node94", 
"@target": "node96"
}
}, 
"node96": {
"edge96": {
"@length": 0.010251, 
"@source": "node96", 
"@target": "node97"
}, 
"edge97": {
"@length": 0.010251, 
"@source": "node96", 
"@target": "node98"
}
}
}, 
"nodeById": {
"node1": {
"@root": true
}, 
"node10": {
"@otu": "otu34"
}, 
"node100": {}, 
"node101": {
"@otu": "otu25"
}, 
"node102": {
"@otu": "otu58"
}, 
"node103": {}, 
"node104": {
"@otu": "otu22"
}, 
"node105": {}, 
"node106": {
"@otu": "otu14"
}, 
"node107": {
"@otu": "otu53"
}, 
"node108": {}, 
"node109": {
"@otu": "otu32"
}, 
"node11": {}, 
"node110": {
"@otu": "otu19"
}, 
"node111": {}, 
"node112": {}, 
"node113": {
"@otu": "otu6"
}, 
"node114": {}, 
"node115": {}, 
"node116": {
"@otu": "otu4"
}, 
"node117": {
"@otu": "otu5"
}, 
"node118": {
"@otu": "otu3"
}, 
"node119": {}, 
"node12": {}, 
"node120": {}, 
"node121": {}, 
"node122": {
"@otu": "otu76"
}, 
"node123": {
"@otu": "otu7"
}, 
"node124": {}, 
"node125": {
"@otu": "otu79"
}, 
"node126": {
"@otu": "otu78"
}, 
"node127": {}, 
"node128": {
"@otu": "otu73"
}, 
"node129": {}, 
"node13": {
"@otu": "otu35"
}, 
"node130": {}, 
"node131": {
"@otu": "otu77"
}, 
"node132": {
"@otu": "otu75"
}, 
"node133": {
"@otu": "otu72"
}, 
"node134": {}, 
"node135": {}, 
"node136": {}, 
"node137": {
"@otu": "otu36"
}, 
"node138": {}, 
"node139": {
"@otu": "otu39"
}, 
"node14": {
"@otu": "otu71"
}, 
"node140": {}, 
"node141": {}, 
"node142": {
"@otu": "otu47"
}, 
"node143": {
"@otu": "otu41"
}, 
"node144": {
"@otu": "otu42"
}, 
"node145": {}, 
"node146": {}, 
"node147": {
"@otu": "otu38"
}, 
"node148": {
"@otu": "otu44"
}, 
"node149": {
"@otu": "otu46"
}, 
"node15": {
"@otu": "otu33"
}, 
"node150": {}, 
"node151": {}, 
"node152": {}, 
"node153": {}, 
"node154": {
"@otu": "otu43"
}, 
"node155": {
"@otu": "otu45"
}, 
"node156": {
"@otu": "otu37"
}, 
"node157": {
"@otu": "otu40"
}, 
"node158": {
"@otu": "otu74"
}, 
"node159": {}, 
"node16": {}, 
"node160": {
"@otu": "otu2"
}, 
"node161": {
"@otu": "otu1"
}, 
"node17": {
"@otu": "otu48"
}, 
"node18": {
"@otu": "otu81"
}, 
"node19": {}, 
"node2": {}, 
"node20": {}, 
"node21": {}, 
"node22": {
"@otu": "otu62"
}, 
"node23": {
"@otu": "otu64"
}, 
"node24": {}, 
"node25": {
"@otu": "otu68"
}, 
"node26": {
"@otu": "otu65"
}, 
"node27": {}, 
"node28": {}, 
"node29": {
"@otu": "otu69"
}, 
"node3": {}, 
"node30": {
"@otu": "otu59"
}, 
"node31": {}, 
"node32": {}, 
"node33": {}, 
"node34": {
"@otu": "otu66"
}, 
"node35": {
"@otu": "otu63"
}, 
"node36": {}, 
"node37": {
"@otu": "otu60"
}, 
"node38": {
"@otu": "otu70"
}, 
"node39": {}, 
"node4": {}, 
"node40": {
"@otu": "otu67"
}, 
"node41": {
"@otu": "otu61"
}, 
"node42": {}, 
"node43": {}, 
"node44": {}, 
"node45": {}, 
"node46": {}, 
"node47": {}, 
"node48": {
"@otu": "otu17"
}, 
"node49": {}, 
"node5": {
"@otu": "otu80"
}, 
"node50": {
"@otu": "otu18"
}, 
"node51": {
"@otu": "otu23"
}, 
"node52": {}, 
"node53": {}, 
"node54": {}, 
"node55": {
"@otu": "otu31"
}, 
"node56": {
"@otu": "otu13"
}, 
"node57": {}, 
"node58": {}, 
"node59": {
"@otu": "otu20"
}, 
"node6": {}, 
"node60": {
"@otu": "otu26"
}, 
"node61": {}, 
"node62": {}, 
"node63": {
"@otu": "otu10"
}, 
"node64": {
"@otu": "otu24"
}, 
"node65": {}, 
"node66": {
"@otu": "otu16"
}, 
"node67": {}, 
"node68": {}, 
"node69": {
"@otu": "otu9"
}, 
"node7": {}, 
"node70": {
"@otu": "otu11"
}, 
"node71": {
"@otu": "otu30"
}, 
"node72": {}, 
"node73": {}, 
"node74": {
"@otu": "otu21"
}, 
"node75": {
"@otu": "otu15"
}, 
"node76": {}, 
"node77": {
"@otu": "otu29"
}, 
"node78": {
"@otu": "otu49"
}, 
"node79": {}, 
"node8": {}, 
"node80": {}, 
"node81": {}, 
"node82": {}, 
"node83": {}, 
"node84": {}, 
"node85": {
"@otu": "otu57"
}, 
"node86": {
"@otu": "otu28"
}, 
"node87": {
"@otu": "otu12"
}, 
"node88": {
"@otu": "otu27"
}, 
"node89": {}, 
"node9": {
"@otu": "otu8"
}, 
"node90": {}, 
"node91": {}, 
"node92": {
"@otu": "otu50"
}, 
"node93": {
"@otu": "otu52"
}, 
"node94": {}, 
"node95": {
"@otu": "otu55"
}, 
"node96": {}, 
"node97": {
"@otu": "otu51"
}, 
"node98": {
"@otu": "otu56"
}, 
"node99": {
"@otu": "otu54"
}
}
}
}
}
}
}
}
