{
"nexml": {
"@about": "#study",
"@generator": "Open Tree API",
"@id": "study",
"@nexml2json": "1.2.1",
"@nexmljson": "http://purl.org/opentree/nexson",
"@version": "0.9",
"@xmlns": {
"$": "http://www.nexml.org/2009",
"nex": "http://www.nexml.org/2009",
"ot": "http://purl.org/opentree-terms#",
"xhtml": "http://www.w3.org/1999/xhtml/vocab#",
"xsd": "http://www.w3.org/2001/XMLSchema#",
"xsi": "http://www.w3.org/2001/XMLSchema-instance"
},
"^ot:agents": {
"agent": [
{
"@description": "Open Tree NexSON validation",
"@id": "peyotl-validator",
"@name": "api.opentreeoflife.org/validate",
"@url": "https://github.com/OpenTreeOfLife/peyotl",
"@version": "0.0.4a",
"invocation": {
"commandLine": [],
"otherProperty": [
{
"name": "pythonVersion",
"value": "3.10.12"
},
{
"name": "pythonImplementation",
"value": "CPython"
}
]
}
},
{
"@description": "Web-based interface for submitting, editing, and reviewing studies in the Open Tree of Life project.",
"@id": "opentree-curation-webapp",
"@name": "OpenTree curation webapp",
"@url": "https://github.com/OpenTreeOfLife/opentree",
"@version": "0.0.0"
}
]
},
"^ot:annotationEvents": {
"annotation": [
{
"@dateCreated": "2025-11-24T08:54:05.513Z",
"@description": "Aids for mapping study OTUs to OTT taxa",
"@id": "otu-mapping-hints",
"@passedChecks": true,
"@preserve": true,
"@wasAssociatedWithAgentId": "opentree-curation-webapp",
"message": [
{
"@code": "OTU_MAPPING_HINTS",
"@humanMessageType": "NONE",
"@severity": "INFO",
"data": {
"autoAcceptExactMatches": false,
"searchContext": {
"$": "All life"
},
"substitutions": {
"substitution": [
{
"@active": false,
"@valid": true,
"new": {
"$": ""
},
"old": {
"$": ""
}
}
]
},
"useFuzzyMatching": true
},
"refersTo": {
"@top": {
"$": "meta"
}
}
}
]
},
{
"@dateCreated": "2025-11-24T08:54:05.513Z",
"@description": "Describes external namesets merged into this study",
"@id": "merged-namesets-metadata",
"@passedChecks": true,
"@preserve": true,
"@wasAssociatedWithAgentId": "opentree-curation-webapp",
"message": [
{
"@code": "MERGED_NAMESET_INFO",
"@humanMessageType": "NONE",
"@severity": "INFO",
"data": {
"namesets": {
"nameset": []
}
},
"refersTo": {
"@top": {
"$": "meta"
}
}
}
]
},
{
"@dateCreated": "2025-11-24T08:54:05.513Z",
"@description": "Describes supporting data files for this study",
"@id": "supporting-files-metadata",
"@passedChecks": true,
"@preserve": true,
"@wasAssociatedWithAgentId": "opentree-curation-webapp",
"message": [
{
"@code": "SUPPORTING_FILE_INFO",
"@humanMessageType": "NONE",
"@severity": "INFO",
"data": {
"@movedToPermanentArchive": false,
"files": {
"file": [
{
"@filename": "figtree_noEuk_Myr.tre",
"@size": 8608,
"@type": "newick",
"@url": "/curator/download/supporting_files.doc.aee8b5a57f017d3d.666967747265655f6e6f45756b5f4d79722e747265.tre",
"description": {
"$": "Source data for tree(s) 'tree5'"
},
"sourceForTree": [
{
"$": "tree5"
}
]
}
]
}
},
"refersTo": {
"@top": {
"$": "meta"
}
}
}
]
}
]
},
"^ot:candidateTreeForSynthesis": [],
"^ot:comment": "",
"^ot:curatorName": [
"jdduke24",
"Mark T. Holder"
],
"^ot:dataDeposit": {
"@href": "https://doi.org/10.5061/dryad.1c59zw42s"
},
"^ot:focalCladeOTTTaxonName": "",
"^ot:otusElementOrder": [
"otus1"
],
"^ot:studyId": "ot_3064",
"^ot:studyPublication": {
"@href": "https://doi.org/10.1093/sysbio/syae071"
},
"^ot:studyPublicationReference": "Wang, S., & Luo, H. (2025). Dating the Bacterial Tree of Life Based on Ancient Symbiosis. Systematic Biology, 74(4), 639\u2013655. https://doi.org/10.1093/sysbio/syae071\n",
"^ot:studyYear": 2025,
"^ot:tag": [],
"^ot:treesElementOrder": [
"trees1"
],
"^xhtml:license": {
"@href": "",
"@name": ""
},
"highestMintedElementIDs": {
"agent": 0,
"annotation": 0,
"edge": 826,
"message": 0,
"node": 829,
"otu": 419,
"otus": 8,
"tree": 5,
"trees": 6
},
"otusById": {
"otus1": {
"otuById": {
"otu10": {
"^ot:originalLabel": "Armatimonadetes bacterium UBA1398",
"^ot:ottId": 7006294,
"^ot:ottTaxonName": "Armatimonadetes bacterium UBA1398"
},
"otu100": {
"^ot:originalLabel": "bacterium HR11",
"^ot:ottId": 7041370,
"^ot:ottTaxonName": "bacterium HR11"
},
"otu101": {
"^ot:originalLabel": "Candidatus Aminicenantes bacterium UBA6072",
"^ot:ottId": 7011068,
"^ot:ottTaxonName": "Candidatus Aminicenantes bacterium UBA6072"
},
"otu102": {
"^ot:originalLabel": "Hippea jasoniae",
"^ot:ottId": 490492,
"^ot:ottTaxonName": "Hippea jasoniae"
},
"otu103": {
"^ot:originalLabel": "Thermocrinis minervae",
"^ot:ottId": 4791355,
"^ot:ottTaxonName": "Thermocrinis minervae"
},
"otu104": {
"^ot:originalLabel": "Deferribacter desulfuricans SSM1",
"^ot:ottId": 667579,
"^ot:ottTaxonName": "Deferribacter desulfuricans SSM1"
},
"otu105": {
"^ot:originalLabel": "Candidatus Dependentiae bacterium",
"^ot:ottId": 7040206,
"^ot:ottTaxonName": "Candidatus Dependentiae bacterium"
},
"otu106": {
"^ot:originalLabel": "Phycisphaerales bacterium UBA5793",
"^ot:ottId": 7022837,
"^ot:ottTaxonName": "Phycisphaerales bacterium UBA5793"
},
"otu107": {
"^ot:originalLabel": "Phycisphaerales bacterium Planc 01",
"^ot:ottId": 5580665,
"^ot:ottTaxonName": "Phycisphaerales bacterium Planc_01"
},
"otu108": {
"^ot:originalLabel": "bacterium HR36",
"^ot:ottId": 7041395,
"^ot:ottTaxonName": "bacterium HR36"
},
"otu109": {
"^ot:originalLabel": "Planctomycetes bacterium RIFCSPLOWO2 12 FULL 50 35",
"^ot:ottId": 5896495,
"^ot:ottTaxonName": "Planctomycetes bacterium RIFCSPLOWO2_12_FULL_50_35"
},
"otu11": {
"^ot:originalLabel": "Abditibacterium utsteinense",
"^ot:ottId": 7001798,
"^ot:ottTaxonName": "Abditibacterium utsteinense"
},
"otu110": {
"^ot:originalLabel": "Planctomycetes bacterium GCA 002748355.1"
},
"otu111": {
"^ot:originalLabel": "Planctomycetes bacterium UBA1662",
"^ot:ottId": 7023055,
"^ot:ottTaxonName": "Planctomycetes bacterium UBA1662"
},
"otu112": {
"^ot:originalLabel": "Planctomycetes bacterium",
"^ot:ottId": 7022965,
"^ot:ottTaxonName": "Planctomycetes bacterium"
},
"otu113": {
"^ot:originalLabel": "bacterium"
},
"otu114": {
"^ot:originalLabel": "Planctomycetes bacterium GCA 002746535.1"
},
"otu115": {
"^ot:originalLabel": "Kiritimatiellales bacterium",
"^ot:ottId": 7022627,
"^ot:ottTaxonName": "Kiritimatiellales bacterium"
},
"otu116": {
"^ot:originalLabel": "Lentisphaeria bacterium UBA7640",
"^ot:ottId": 7022648,
"^ot:ottTaxonName": "Lentisphaeria bacterium UBA7640"
},
"otu117": {
"^ot:originalLabel": "Verrucomicrobiales bacterium",
"^ot:ottId": 7041053,
"^ot:ottTaxonName": "Verrucomicrobiales bacterium"
},
"otu118": {
"^ot:originalLabel": "Parachlamydia acanthamoebae",
"^ot:ottId": 324538,
"^ot:ottTaxonName": "Parachlamydia acanthamoebae"
},
"otu119": {
"^ot:originalLabel": "Candidatus Clavichlamydia salmonicola-GCA 015356765.1"
},
"otu12": {
"^ot:originalLabel": "Chthonomonas calidirosea T49",
"^ot:ottId": 4790758,
"^ot:ottTaxonName": "Chthonomonas calidirosea T49"
},
"otu120": {
"^ot:originalLabel": "Candidatus Rhabdochlamydia sp W815-GCA 018642185.1"
},
"otu121": {
"^ot:originalLabel": "Omnitrophica bacterium RIFCSPLOWO2 12 FULL 44 17",
"^ot:ottId": 5888956,
"^ot:ottTaxonName": "Omnitrophica bacterium RIFCSPLOWO2_12_FULL_44_17"
},
"otu122": {
"^ot:originalLabel": "Chlorobium limicola DSM 245",
"^ot:ottId": 845140,
"^ot:ottTaxonName": "Chlorobium limicola DSM 245"
},
"otu123": {
"^ot:altLabel": "Bacteroidetes bacterium CG12",
"^ot:originalLabel": "Bacteroidetes bacterium CG12 big fil rev 8 21 14 0 65 60 17"
},
"otu124": {
"^ot:originalLabel": "Blattabacterium sp Nauphoeta cinerea -GCA 000471965.1"
},
"otu125": {
"^ot:originalLabel": "Blattabacterium clevelandi-GCA 003268615.1"
},
"otu126": {
"^ot:originalLabel": "Candidatus Marinimicrobia bacterium CG1 02 48 14",
"^ot:ottId": 5889102,
"^ot:ottTaxonName": "Candidatus Marinimicrobia bacterium CG1_02_48_14"
},
"otu127": {
"^ot:originalLabel": "Candidatus Raymondbacteria bacterium RIFOXYA2 FULL 49 16",
"^ot:ottId": 5889169,
"^ot:ottTaxonName": "Candidatus Raymondbacteria bacterium RIFOXYA2_FULL_49_16"
},
"otu128": {
"^ot:originalLabel": "Fibrobacter sp UWP2",
"^ot:ottId": 5994869,
"^ot:ottTaxonName": "Fibrobacter sp. UWP2"
},
"otu129": {
"^ot:originalLabel": "Chitinivibrio alkaliphilus ACht1",
"^ot:ottId": 4746748,
"^ot:ottTaxonName": "Chitinivibrio alkaliphilus ACht1"
},
"otu13": {
"^ot:originalLabel": "Candidatus Eremiobacteraeota bacterium",
"^ot:ottId": 7011221,
"^ot:ottTaxonName": "Candidatus Eremiobacteraeota bacterium"
},
"otu130": {
"^ot:originalLabel": "Gemmatimonadetes bacterium",
"^ot:ottId": 7022577,
"^ot:ottTaxonName": "Gemmatimonadetes bacterium"
},
"otu131": {
"^ot:originalLabel": "Cloacimonetes bacterium UBA3541",
"^ot:ottId": 7011156,
"^ot:ottTaxonName": "Cloacimonetes bacterium UBA3541"
},
"otu132": {
"^ot:originalLabel": "Elusimicrobia bacterium CG1 02 37 114",
"^ot:ottId": 5890797,
"^ot:ottTaxonName": "Elusimicrobia bacterium CG1_02_37_114"
},
"otu133": {
"^ot:originalLabel": "Candidatus Endomicrobium trichonymphae-GCA 001730735.1"
},
"otu134": {
"^ot:originalLabel": "Endomicrobiaceae bacterium-GCA 016292265.1"
},
"otu135": {
"^ot:originalLabel": "Leptospira levettii",
"^ot:ottId": 7039836,
"^ot:ottTaxonName": "Leptospira levettii"
},
"otu136": {
"^ot:originalLabel": "Spirochaetes bacterium GWB1 27 13",
"^ot:ottId": 5913420,
"^ot:ottTaxonName": "Spirochaetes bacterium GWB1_27_13"
},
"otu137": {
"^ot:originalLabel": "Treponema primitia ZAS-1-GCA 000297095.1"
},
"otu138": {
"^ot:originalLabel": "Breznakiella homolactica-GCA 016616095.1"
},
"otu139": {
"^ot:originalLabel": "Treponema sp OMZ 806-GCA 018336815.1"
},
"otu14": {
"^ot:originalLabel": "bacterium UBP9 UBA4705",
"^ot:ottId": 7041691,
"^ot:ottTaxonName": "bacterium UBP9_UBA4705"
},
"otu140": {
"^ot:originalLabel": "Treponema denticola F0402-GCA 000191825.1"
},
"otu141": {
"^ot:originalLabel": "Treponema brennaborense DSM 12168-GCA 000212415.1"
},
"otu142": {
"^ot:originalLabel": "Spirochaetes bacterium-GCA 016285315.1"
},
"otu143": {
"^ot:originalLabel": "Borrelia hispanica CRI",
"^ot:ottId": 5294170,
"^ot:ottTaxonName": "Borrelia hispanica CRI"
},
"otu144": {
"^ot:originalLabel": "Spirochaetes bacterium GWF1 51 8",
"^ot:ottId": 5913437,
"^ot:ottTaxonName": "Spirochaetes bacterium GWF1_51_8"
},
"otu145": {
"^ot:originalLabel": "Brachyspira hyodysenteriae ATCC 27164",
"^ot:ottId": 149544,
"^ot:ottTaxonName": "Brachyspira hyodysenteriae ATCC 27164"
},
"otu146": {
"^ot:originalLabel": "Spirochaetia bacterium UBA6919",
"^ot:ottId": 7040126,
"^ot:ottTaxonName": "Spirochaetia bacterium UBA6919"
},
"otu147": {
"^ot:originalLabel": "bacterium GBS-1",
"^ot:ottId": 5568327,
"^ot:ottTaxonName": "bacterium GBS-1"
},
"otu148": {
"^ot:originalLabel": "Marinithermus hydrothermalis DSM 14884",
"^ot:ottId": 1004489,
"^ot:ottTaxonName": "Marinithermus hydrothermalis DSM 14884"
},
"otu149": {
"^ot:originalLabel": "Pseudothermotoga thermarum DSM 5069",
"^ot:ottId": 652294,
"^ot:ottTaxonName": "Pseudothermotoga thermarum DSM 5069"
},
"otu15": {
"^ot:originalLabel": "SAR202 cluster bacterium bin16",
"^ot:ottId": 7011980,
"^ot:ottTaxonName": "SAR202 cluster bacterium bin16"
},
"otu150": {
"^ot:originalLabel": "Leptotrichia sp oral taxon 847",
"^ot:ottId": 5896225,
"^ot:ottTaxonName": "Leptotrichia sp. oral taxon 847"
},
"otu16": {
"^ot:originalLabel": "Thermogemmatispora onikobensis",
"^ot:ottId": 620867,
"^ot:ottTaxonName": "Thermogemmatispora onikobensis"
},
"otu167": {
"^ot:originalLabel": "Chloroflexi bacterium GCA 317106510.0",
"^ot:ottId": 7011703,
"^ot:ottTaxonName": "Chloroflexi bacterium"
},
"otu17": {
"^ot:originalLabel": "Chloroflexi bacterium GCA 003171065.1"
},
"otu18": {
"^ot:originalLabel": "Candidatus Dormibacteraeota bacterium",
"^ot:ottId": 7011214,
"^ot:ottTaxonName": "Candidatus Dormibacteraeota bacterium"
},
"otu184": {
"^ot:originalLabel": "Texas Phoenix palm phytoplasma-GCA 577468520.0",
"^ot:ottId": 502273,
"^ot:ottTaxonName": "Texas Phoenix palm phytoplasma"
},
"otu185": {
"^ot:originalLabel": "Catharanthus roseus aster yellows phytoplasma-GCA 421487510.0",
"^ot:ottId": 693409,
"^ot:ottTaxonName": "'Catharanthus roseus' aster yellows phytoplasma"
},
"otu186": {
"^ot:originalLabel": "Mycoplasma gypis-GCA 1692477510.0",
"^ot:ottId": 306552,
"^ot:ottTaxonName": "Mycoplasma gypis"
},
"otu187": {
"^ot:originalLabel": "Mycoplasma penetrans HF-2-GCA 1122510.0",
"^ot:ottId": 795259,
"^ot:ottTaxonName": "Mycoplasma penetrans HF-2"
},
"otu19": {
"^ot:originalLabel": "Candidatus Giovannonibacteria bacterium RIFCSPLOWO2 12 FULL 44 15",
"^ot:ottId": 5887746,
"^ot:ottTaxonName": "Candidatus Giovannonibacteria bacterium RIFCSPLOWO2_12_FULL_44_15"
},
"otu196": {
"^ot:originalLabel": "Candidatus Finniella inopinata-GCA 421030510.0",
"^ot:ottId": 5900985,
"^ot:ottTaxonName": "Candidatus Finniella inopinata"
},
"otu197": {
"^ot:originalLabel": "Caedimonas varicaedens-GCA 119265510.0",
"^ot:ottId": 927440,
"^ot:ottTaxonName": "Caedimonas varicaedens"
},
"otu198": {
"^ot:originalLabel": "Wolbachia endosymbiont of Cylisticus convexus-GCA 334434510.0",
"^ot:ottId": 307579,
"^ot:ottTaxonName": "Wolbachia endosymbiont of Cylisticus convexus"
},
"otu199": {
"^ot:originalLabel": "Neorickettsia sp 179522-GCA 159353510.0",
"^ot:ottId": 5900841,
"^ot:ottTaxonName": "Neorickettsia sp. 179522"
},
"otu20": {
"^ot:originalLabel": "Candidatus Andersenbacteria bacterium RIFCSPHIGHO2 02 FULL 45 11",
"^ot:ottId": 5887464,
"^ot:ottTaxonName": "Candidatus Andersenbacteria bacterium RIFCSPHIGHO2_02_FULL_45_11"
},
"otu200": {
"^ot:originalLabel": "Rickettsiales bacterium-GCA 1678062510.0",
"^ot:ottId": 7027220,
"^ot:ottTaxonName": "Rickettsiales bacterium"
},
"otu21": {
"^ot:originalLabel": "Patescibacteria group bacterium UBA2591",
"^ot:ottId": 7007063,
"^ot:ottTaxonName": "Patescibacteria group bacterium UBA2591"
},
"otu22": {
"^ot:originalLabel": "Candidatus Uhrbacteria bacterium RIFOXYA2 FULL 40 9",
"^ot:ottId": 5888488,
"^ot:ottTaxonName": "Candidatus Uhrbacteria bacterium RIFOXYA2_FULL_40_9"
},
"otu23": {
"^ot:altLabel": "Candidatus Berkelbacteria bacterium CG10",
"^ot:originalLabel": "Candidatus Berkelbacteria bacterium CG10 big fil rev 8 21 14 0 10 41 12"
},
"otu232": {
"^ot:originalLabel": "Buchnera aphidicola Cinara tujafilina -GCA 21763510.0",
"^ot:ottId": 632024,
"^ot:ottTaxonName": "Buchnera aphidicola (Cinara tujafilina)"
},
"otu233": {
"^ot:originalLabel": "Buchnera aphidicola Tuberolachnus salignus -GCA 90001678510.0",
"^ot:ottId": 478411,
"^ot:ottTaxonName": "Buchnera aphidicola (Tuberolachnus salignus)"
},
"otu234": {
"^ot:originalLabel": "Coxiella-like endosymbiont-GCA 287109510.0",
"^ot:ottId": 5587922,
"^ot:ottTaxonName": "Coxiella-like endosymbiont"
},
"otu235": {
"^ot:originalLabel": "Coxiella burnetii str Schperling-GCA 263406510.0",
"^ot:ottId": 5288817,
"^ot:ottTaxonName": "Coxiella burnetii str. Schperling"
},
"otu236": {
"^ot:originalLabel": "Candidatus Berkiella aquae-GCA 143129510.0",
"^ot:ottId": 4790683,
"^ot:ottTaxonName": "Candidatus Berkiella aquae"
},
"otu24": {
"^ot:originalLabel": "Candidatus Peregrinibacteria bacterium GW2011 GWF2 39 17",
"^ot:ottId": 5573541,
"^ot:ottTaxonName": "Candidatus Peregrinibacteria bacterium GW2011_GWF2_39_17"
},
"otu25": {
"^ot:originalLabel": "candidate division CPR3 bacterium 4484 211",
"^ot:ottId": 7041729,
"^ot:ottTaxonName": "candidate division CPR3 bacterium 4484_211"
},
"otu26": {
"^ot:originalLabel": "candidate division WWE3 bacterium GW2011 GWC2 41 23",
"^ot:ottId": 5573486,
"^ot:ottTaxonName": "candidate division WWE3 bacterium GW2011_GWC2_41_23"
},
"otu260": {
"^ot:originalLabel": "Planctomycetes bacterium GCA 274835510.0"
},
"otu264": {
"^ot:originalLabel": "Planctomycetes bacterium GCA 274653510.0"
},
"otu269": {
"^ot:originalLabel": "Candidatus Clavichlamydia salmonicola-GCA 1535676510.0",
"^ot:ottId": 278289,
"^ot:ottTaxonName": "Candidatus Clavichlamydia salmonicola"
},
"otu27": {
"^ot:originalLabel": "Candidatus Roizmanbacteria bacterium RIFCSPHIGHO2 12 FULL 37 23",
"^ot:ottId": 5888242,
"^ot:ottTaxonName": "Candidatus Roizmanbacteria bacterium RIFCSPHIGHO2_12_FULL_37_23"
},
"otu270": {
"^ot:altLabel": "Candidatus Rhabdochlamydia sp W815",
"^ot:originalLabel": "Candidatus Rhabdochlamydia sp W815-GCA 1864218510.0"
},
"otu274": {
"^ot:originalLabel": "Blattabacterium sp Nauphoeta cinerea -GCA 47196510.0",
"^ot:ottId": 5254632,
"^ot:ottTaxonName": "Blattabacterium sp. (Nauphoeta cinerea)"
},
"otu275": {
"^ot:originalLabel": "Blattabacterium clevelandi-GCA 326861510.0",
"^ot:ottId": 187368,
"^ot:ottTaxonName": "Blattabacterium clevelandi"
},
"otu28": {
"^ot:originalLabel": "Candidatus Dojkabacteria bacterium HGW-Dojkabacteria-1",
"^ot:ottId": 7011033,
"^ot:ottTaxonName": "Candidatus Dojkabacteria bacterium HGW-Dojkabacteria-1"
},
"otu283": {
"^ot:originalLabel": "Candidatus Endomicrobium trichonymphae-GCA 173073510.0",
"^ot:ottId": 5177061,
"^ot:ottTaxonName": "Candidatus Endomicrobium trichonymphae"
},
"otu284": {
"^ot:altLabel": "Endomicrobiaceae bacterium",
"^ot:originalLabel": "Endomicrobiaceae bacterium-GCA 1629226510.0"
},
"otu287": {
"^ot:originalLabel": "Treponema primitia ZAS-1-GCA 29709510.0",
"^ot:ottId": 373375,
"^ot:ottTaxonName": "Treponema primitia ZAS-1"
},
"otu288": {
"^ot:altLabel": "Breznakiella homolactica",
"^ot:originalLabel": "Breznakiella homolactica-GCA 1661609510.0"
},
"otu289": {
"^ot:originalLabel": "Treponema sp OMZ 806-GCA 1833681510.0",
"^ot:ottId": 5913406,
"^ot:ottTaxonName": "Treponema sp. OMZ 806"
},
"otu29": {
"^ot:originalLabel": "Candidatus Saccharibacteria bacterium UBA1788",
"^ot:ottId": 7010957,
"^ot:ottTaxonName": "Candidatus Saccharibacteria bacterium UBA1788"
},
"otu290": {
"^ot:originalLabel": "Treponema denticola F0402-GCA 19182510.0",
"^ot:ottId": 244889,
"^ot:ottTaxonName": "Treponema denticola F0402"
},
"otu291": {
"^ot:originalLabel": "Treponema brennaborense DSM 12168-GCA 21241510.0",
"^ot:ottId": 57520,
"^ot:ottTaxonName": "Treponema brennaborense DSM 12168"
},
"otu292": {
"^ot:originalLabel": "Spirochaetes bacterium-GCA 1628531510.0",
"^ot:ottId": 7040117,
"^ot:ottTaxonName": "Spirochaetes bacterium"
},
"otu3": {
"^ot:originalLabel": "Candidatus Sericytochromatia bacterium S15B-MN24 CBMW 12",
"^ot:ottId": 7012007,
"^ot:ottTaxonName": "Candidatus Sericytochromatia bacterium S15B-MN24 CBMW_12"
},
"otu30": {
"^ot:originalLabel": "Tepidanaerobacter syntrophicus JL",
"^ot:ottId": 751202,
"^ot:ottTaxonName": "Tepidanaerobacter syntrophicus"
},
"otu31": {
"^ot:originalLabel": "Natranaerobius trueperi",
"^ot:ottId": 447874,
"^ot:ottTaxonName": "Natranaerobius trueperi"
},
"otu32": {
"^ot:originalLabel": "Marininema mesophilum",
"^ot:ottId": 473549,
"^ot:ottTaxonName": "Marininema mesophilum"
},
"otu33": {
"^ot:originalLabel": "Bacillus subtilis",
"^ot:ottId": 1084928,
"^ot:ottTaxonName": "Bacillus subtilis"
},
"otu34": {
"^ot:originalLabel": "Texas Phoenix palm phytoplasma-GCA 005774685.2"
},
"otu35": {
"^ot:originalLabel": "Catharanthus roseus aster yellows phytoplasma-GCA 004214875.1"
},
"otu36": {
"^ot:originalLabel": "Mycoplasma gypis-GCA 016924775.1"
},
"otu37": {
"^ot:originalLabel": "Mycoplasma penetrans HF-2-GCA 000011225.1"
},
"otu38": {
"^ot:originalLabel": "Ammonifex degensii KC4",
"^ot:ottId": 675900,
"^ot:ottTaxonName": "Ammonifex degensii KC4"
},
"otu39": {
"^ot:originalLabel": "Limnochorda pilosa",
"^ot:ottId": 5613952,
"^ot:ottTaxonName": "Limnochorda pilosa"
},
"otu4": {
"^ot:originalLabel": "Xenococcus sp PCC 7305",
"^ot:ottId": 28936,
"^ot:ottTaxonName": "Xenococcus sp. PCC 7305"
},
"otu40": {
"^ot:originalLabel": "Acetohalobium arabaticum DSM 5501",
"^ot:ottId": 498263,
"^ot:ottTaxonName": "Acetohalobium arabaticum DSM 5501"
},
"otu41": {
"^ot:originalLabel": "Nocardiopsis sp TSRI0078",
"^ot:ottId": 5885798,
"^ot:ottTaxonName": "Nocardiopsis sp. TSRI0078"
},
"otu42": {
"^ot:originalLabel": "Rubrobacter radiotolerans DSM 5868",
"^ot:ottId": 217788,
"^ot:ottTaxonName": "Rubrobacter radiotolerans DSM 5868"
},
"otu43": {
"^ot:originalLabel": "Olegusella massiliensis",
"^ot:ottId": 5885932,
"^ot:ottTaxonName": "Olegusella massiliensis"
},
"otu44": {
"^ot:originalLabel": "Actinobacteria bacterium UBA2594",
"^ot:ottId": 7002294,
"^ot:ottTaxonName": "Actinobacteria bacterium UBA2594"
},
"otu45": {
"^ot:originalLabel": "Magnetococcales bacterium DC0425bin3",
"^ot:ottId": 7023611,
"^ot:ottTaxonName": "Magnetococcales bacterium DC0425bin3"
},
"otu46": {
"^ot:originalLabel": "Candidatus Finniella inopinata-GCA 004210305.1"
},
"otu47": {
"^ot:originalLabel": "Caedimonas varicaedens-GCA 001192655.1"
},
"otu48": {
"^ot:originalLabel": "Wolbachia endosymbiont of Cylisticus convexus-GCA 003344345.1"
},
"otu49": {
"^ot:originalLabel": "Neorickettsia sp 179522-GCA 001593535.1"
},
"otu5": {
"^ot:originalLabel": "Nostoc sp PCC 7107",
"^ot:ottId": 851415,
"^ot:ottTaxonName": "Nostoc sp. PCC 7107"
},
"otu50": {
"^ot:originalLabel": "Rickettsiales bacterium-GCA 016780625.1"
},
"otu51": {
"^ot:originalLabel": "Dictyostelium discoideum",
"^ot:ottId": 160850,
"^ot:ottTaxonName": "Dictyostelium discoideum"
},
"otu52": {
"^ot:originalLabel": "Polysphondylium pallidum"
},
"otu53": {
"^ot:originalLabel": "Acanthamoeba castellanii",
"^ot:ottId": 120245,
"^ot:ottTaxonName": "Acanthamoeba castellanii"
},
"otu54": {
"^ot:originalLabel": "Drosophila melanogaster",
"^ot:ottId": 505714,
"^ot:ottTaxonName": "Drosophila melanogaster"
},
"otu55": {
"^ot:originalLabel": "Daphnia pulex",
"^ot:ottId": 59086,
"^ot:ottTaxonName": "Daphnia pulex"
},
"otu56": {
"^ot:originalLabel": "Caenorhabditis elegans",
"^ot:ottId": 395048,
"^ot:ottTaxonName": "Caenorhabditis elegans"
},
"otu57": {
"^ot:originalLabel": "Branchiostoma floridae",
"^ot:ottId": 176532,
"^ot:ottTaxonName": "Branchiostoma floridae"
},
"otu58": {
"^ot:originalLabel": "Gallus gallus",
"^ot:ottId": 153563,
"^ot:ottTaxonName": "Gallus gallus"
},
"otu59": {
"^ot:originalLabel": "Homo sapiens",
"^ot:ottId": 770315,
"^ot:ottTaxonName": "Homo sapiens"
},
"otu6": {
"^ot:originalLabel": "Oscillatoria sp PCC 10802",
"^ot:ottId": 892074,
"^ot:ottTaxonName": "Oscillatoria sp. PCC 10802"
},
"otu60": {
"^ot:originalLabel": "Amphimedon queenslandica",
"^ot:ottId": 707499,
"^ot:ottTaxonName": "Amphimedon queenslandica"
},
"otu61": {
"^ot:originalLabel": "Salpingoeca rosetta",
"^ot:ottId": 1002450,
"^ot:ottTaxonName": "Salpingoeca rosetta"
},
"otu62": {
"^ot:originalLabel": "Pleurotus ostreatus",
"^ot:ottId": 581149,
"^ot:ottTaxonName": "Pleurotus ostreatus"
},
"otu63": {
"^ot:originalLabel": "Ustilago maydis",
"^ot:ottId": 285447,
"^ot:ottTaxonName": "Ustilago maydis"
},
"otu64": {
"^ot:originalLabel": "Candida albicans",
"^ot:ottId": 154960,
"^ot:ottTaxonName": "Candida albicans"
},
"otu65": {
"^ot:originalLabel": "Spizellomyces punctatus",
"^ot:ottId": 708156,
"^ot:ottTaxonName": "Spizellomyces punctatus"
},
"otu66": {
"^ot:originalLabel": "Paramecium tetraurelia",
"^ot:ottId": 568130,
"^ot:ottTaxonName": "Paramecium tetraurelia"
},
"otu67": {
"^ot:originalLabel": "Oxytricha trifallax",
"^ot:ottId": 450811,
"^ot:ottTaxonName": "Oxytricha trifallax"
},
"otu68": {
"^ot:originalLabel": "Symbiodinium minutum"
},
"otu69": {
"^ot:originalLabel": "Phytophthora infestans",
"^ot:ottId": 775725,
"^ot:ottTaxonName": "Phytophthora infestans"
},
"otu7": {
"^ot:originalLabel": "Gloeobacter violaceus PCC 7421",
"^ot:ottId": 37488,
"^ot:ottTaxonName": "Gloeobacter violaceus PCC 7421"
},
"otu70": {
"^ot:originalLabel": "Thalassiosira pseudonana",
"^ot:ottId": 753596,
"^ot:ottTaxonName": "Thalassiosira pseudonana"
},
"otu71": {
"^ot:originalLabel": "Oryza sativa",
"^ot:ottId": 709894,
"^ot:ottTaxonName": "Oryza sativa"
},
"otu72": {
"^ot:originalLabel": "Arabidopsis thaliana",
"^ot:ottId": 309263,
"^ot:ottTaxonName": "Arabidopsis thaliana"
},
"otu73": {
"^ot:originalLabel": "Physcomitrella patens",
"^ot:ottId": 821359,
"^ot:ottTaxonName": "Physcomitrella patens"
},
"otu74": {
"^ot:originalLabel": "Ostreococcus tauri",
"^ot:ottId": 772469,
"^ot:ottTaxonName": "Ostreococcus tauri"
},
"otu75": {
"^ot:originalLabel": "Cyanidioschyzon merolae",
"^ot:ottId": 85503,
"^ot:ottTaxonName": "Cyanidioschyzon merolae"
},
"otu76": {
"^ot:originalLabel": "Porphyra umbilicalis",
"^ot:ottId": 726207,
"^ot:ottTaxonName": "Porphyra umbilicalis"
},
"otu77": {
"^ot:originalLabel": "Chondrus crispus",
"^ot:ottId": 878946,
"^ot:ottTaxonName": "Chondrus crispus"
},
"otu78": {
"^ot:originalLabel": "Cyanophora paradoxa",
"^ot:ottId": 878960,
"^ot:ottTaxonName": "Cyanophora paradoxa"
},
"otu79": {
"^ot:originalLabel": "Andalucia godoyi",
"^ot:ottId": 83127,
"^ot:ottTaxonName": "Andalucia godoyi"
},
"otu8": {
"^ot:originalLabel": "candidate division WOR-1 bacterium RIFOXYB2 FULL 45 9",
"^ot:ottId": 5916826,
"^ot:ottTaxonName": "candidate division WOR-1 bacterium RIFOXYB2_FULL_45_9"
},
"otu80": {
"^ot:originalLabel": "Mariprofundus micogutta",
"^ot:ottId": 7039713,
"^ot:ottTaxonName": "Mariprofundus micogutta"
},
"otu81": {
"^ot:originalLabel": "Escherichia coli str K-12 substr W3110",
"^ot:ottId": 756477,
"^ot:ottTaxonName": "Escherichia coli str. K-12 substr. W3110"
},
"otu82": {
"^ot:originalLabel": "Buchnera aphidicola Cinara tujafilina -GCA 000217635.1"
},
"otu83": {
"^ot:originalLabel": "Buchnera aphidicola Tuberolachnus salignus -GCA 900016785.1"
},
"otu84": {
"^ot:originalLabel": "Coxiella-like endosymbiont-GCA 002871095.1"
},
"otu85": {
"^ot:originalLabel": "Coxiella burnetii str Schperling-GCA 002634065.1"
},
"otu86": {
"^ot:originalLabel": "Candidatus Berkiella aquae-GCA 001431295.1"
},
"otu87": {
"^ot:originalLabel": "Thiocapsa marina 5811",
"^ot:ottId": 321832,
"^ot:ottTaxonName": "Thiocapsa marina 5811"
},
"otu88": {
"^ot:originalLabel": "Nitrosococcus oceani ATCC 19707",
"^ot:ottId": 147474,
"^ot:ottTaxonName": "Nitrosococcus oceani ATCC 19707"
},
"otu89": {
"^ot:originalLabel": "Rhodocyclales bacterium GWA2 65 20",
"^ot:ottId": 5904268,
"^ot:ottTaxonName": "Rhodocyclales bacterium GWA2_65_20"
},
"otu9": {
"^ot:originalLabel": "Candidatus Margulisbacteria bacterium",
"^ot:ottId": 7017223,
"^ot:ottTaxonName": "Candidatus Margulisbacteria bacterium"
},
"otu90": {
"^ot:originalLabel": "Neisseria gonorrhoeae FA 1090",
"^ot:ottId": 770027,
"^ot:ottTaxonName": "Neisseria gonorrhoeae FA 1090"
},
"otu91": {
"^ot:altLabel": "Deltaproteobacteria bacterium CG11",
"^ot:originalLabel": "Deltaproteobacteria bacterium CG11 big fil rev 8 21 14 0 20 45 16"
},
"otu92": {
"^ot:originalLabel": "Deltaproteobacteria bacterium UBA6601",
"^ot:ottId": 7030614,
"^ot:ottTaxonName": "Deltaproteobacteria bacterium UBA6601"
},
"otu93": {
"^ot:originalLabel": "Bradymonas sediminis",
"^ot:ottId": 5572888,
"^ot:ottTaxonName": "Bradymonas sediminis"
},
"otu94": {
"^ot:altLabel": "Bdellovibrionales bacterium CG10",
"^ot:originalLabel": "Bdellovibrionales bacterium CG10 big fil rev 8 21 14 0 10 45 34"
},
"otu95": {
"^ot:originalLabel": "Desulfuromonas soudanensis",
"^ot:ottId": 5642302,
"^ot:ottTaxonName": "Desulfuromonas soudanensis"
},
"otu96": {
"^ot:originalLabel": "Nitrospirae bacterium",
"^ot:ottId": 7022741,
"^ot:ottTaxonName": "Nitrospirae bacterium"
},
"otu97": {
"^ot:originalLabel": "Acidobacteria bacterium Mor1",
"^ot:ottId": 5580876,
"^ot:ottTaxonName": "Acidobacteria bacterium Mor1"
},
"otu98": {
"^ot:originalLabel": "Geothrix fermentans DSM 14018",
"^ot:ottId": 844595,
"^ot:ottTaxonName": "Geothrix fermentans DSM 14018"
},
"otu99": {
"^ot:originalLabel": "Holophagales bacterium UBA2201",
"^ot:ottId": 7002037,
"^ot:ottTaxonName": "Holophagales bacterium UBA2201"
}
}
}
},
"treesById": {
"trees1": {
"@otus": "otus1",
"^ot:treeElementOrder": [
"tree5"
],
"treeById": {
"tree5": {
"@label": "bootstrap/1-pf/dating/C60/mcmctree/rrtc/official-mcmc987/marginal/figtree_noEuk.nwk",
"@xsi:type": "nex:FloatTree",
"^ot:branchLengthDescription": "",
"^ot:branchLengthMode": "ot:time",
"^ot:branchLengthTimeUnit": "Myr",
"^ot:curatedType": "Maximum likelihood ",
"^ot:inGroupClade": "node593",
"^ot:nodeLabelDescription": "Date CI",
"^ot:nodeLabelMode": "ot:other",
"^ot:nodeLabelTimeUnit": "",
"^ot:outGroupEdge": "",
"^ot:reasonsToExcludeFromSynthesis": [
{
"$": "Need to update OT Taxonomy before including"
}
],
"^ot:rootNodeId": "node593",
"^ot:specifiedRoot": "node593",
"^ot:tag": [],
"^ot:unrootedTree": false,
"edgeBySourceId": {
"node593": {
"edge591": {
"@length": 19.8191,
"@source": "node593",
"@target": "node594"
},
"edge820": {
"@length": 85.723,
"@source": "node593",
"@target": "node823"
}
},
"node594": {
"edge592": {
"@length": 40.597,
"@source": "node594",
"@target": "node595"
},
"edge675": {
"@length": 134.1947,
"@source": "node594",
"@target": "node678"
}
},
"node595": {
"edge593": {
"@length": 104.5914,
"@source": "node595",
"@target": "node596"
},
"edge606": {
"@length": 58.1726,
"@source": "node595",
"@target": "node609"
}
},
"node596": {
"edge594": {
"@length": 399.6264,
"@source": "node596",
"@target": "node597"
},
"edge603": {
"@length": 541.3296,
"@source": "node596",
"@target": "node606"
}
},
"node597": {
"edge595": {
"@length": 3089.7777,
"@source": "node597",
"@target": "node598"
},
"edge596": {
"@length": 639.1001,
"@source": "node597",
"@target": "node599"
}
},
"node599": {
"edge597": {
"@length": 565.9691,
"@source": "node599",
"@target": "node600"
},
"edge602": {
"@length": 2450.6776,
"@source": "node599",
"@target": "node605"
}
},
"node600": {
"edge598": {
"@length": 185.6897,
"@source": "node600",
"@target": "node601"
},
"edge601": {
"@length": 1884.7085,
"@source": "node600",
"@target": "node604"
}
},
"node601": {
"edge599": {
"@length": 1699.0189,
"@source": "node601",
"@target": "node602"
},
"edge600": {
"@length": 1699.0189,
"@source": "node601",
"@target": "node603"
}
},
"node606": {
"edge604": {
"@length": 2948.0745,
"@source": "node606",
"@target": "node607"
},
"edge605": {
"@length": 2948.0745,
"@source": "node606",
"@target": "node608"
}
},
"node609": {
"edge607": {
"@length": 71.4305,
"@source": "node609",
"@target": "node610"
},
"edge646": {
"@length": 105.1984,
"@source": "node609",
"@target": "node649"
}
},
"node610": {
"edge608": {
"@length": 140.6185,
"@source": "node610",
"@target": "node611"
},
"edge617": {
"@length": 178.1655,
"@source": "node610",
"@target": "node620"
}
},
"node611": {
"edge609": {
"@length": 451.7143,
"@source": "node611",
"@target": "node612"
},
"edge614": {
"@length": 268.8188,
"@source": "node611",
"@target": "node617"
}
},
"node612": {
"edge610": {
"@length": 197.0057,
"@source": "node612",
"@target": "node613"
},
"edge613": {
"@length": 2872.0596,
"@source": "node612",
"@target": "node616"
}
},
"node613": {
"edge611": {
"@length": 2675.0539,
"@source": "node613",
"@target": "node614"
},
"edge612": {
"@length": 2675.0539,
"@source": "node613",
"@target": "node615"
}
},
"node617": {
"edge615": {
"@length": 3054.9551,
"@source": "node617",
"@target": "node618"
},
"edge616": {
"@length": 3054.9551,
"@source": "node617",
"@target": "node619"
}
},
"node620": {
"edge618": {
"@length": 334,
"@source": "node620",
"@target": "node621"
},
"edge625": {
"@length": 266.5552,
"@source": "node620",
"@target": "node628"
}
},
"node621": {
"edge619": {
"@length": 79.796,
"@source": "node621",
"@target": "node622"
},
"edge624": {
"@length": 2952.227,
"@source": "node621",
"@target": "node627"
}
},
"node622": {
"edge620": {
"@length": 470.2072,
"@source": "node622",
"@target": "node623"
},
"edge623": {
"@length": 2872.431,
"@source": "node622",
"@target": "node626"
}
},
"node623": {
"edge621": {
"@length": 2402.2238,
"@source": "node623",
"@target": "node624"
},
"edge622": {
"@length": 2402.2238,
"@source": "node623",
"@target": "node625"
}
},
"node628": {
"edge626": {
"@length": 164.0128,
"@source": "node628",
"@target": "node629"
},
"edge637": {
"@length": 131.0793,
"@source": "node628",
"@target": "node640"
}
},
"node629": {
"edge627": {
"@length": 85.7534,
"@source": "node629",
"@target": "node630"
},
"edge636": {
"@length": 2855.6589,
"@source": "node629",
"@target": "node639"
}
},
"node630": {
"edge628": {
"@length": 181.369,
"@source": "node630",
"@target": "node631"
},
"edge635": {
"@length": 2769.9055,
"@source": "node630",
"@target": "node638"
}
},
"node631": {
"edge629": {
"@length": 295.2122,
"@source": "node631",
"@target": "node632"
},
"edge632": {
"@length": 191.3227,
"@source": "node631",
"@target": "node635"
}
},
"node632": {
"edge630": {
"@length": 2293.3243,
"@source": "node632",
"@target": "node633"
},
"edge631": {
"@length": 2293.3243,
"@source": "node632",
"@target": "node634"
}
},
"node635": {
"edge633": {
"@length": 2397.2138,
"@source": "node635",
"@target": "node636"
},
"edge634": {
"@length": 2397.2138,
"@source": "node635",
"@target": "node637"
}
},
"node640": {
"edge638": {
"@length": 153.3804,
"@source": "node640",
"@target": "node641"
},
"edge645": {
"@length": 2888.5924,
"@source": "node640",
"@target": "node648"
}
},
"node641": {
"edge639": {
"@length": 306.7137,
"@source": "node641",
"@target": "node642"
},
"edge644": {
"@length": 2735.212,
"@source": "node641",
"@target": "node647"
}
},
"node642": {
"edge640": {
"@length": 2428.4983,
"@source": "node642",
"@target": "node643"
},
"edge641": {
"@length": 101.9007,
"@source": "node642",
"@target": "node644"
}
},
"node644": {
"edge642": {
"@length": 2326.5975,
"@source": "node644",
"@target": "node645"
},
"edge643": {
"@length": 2326.5975,
"@source": "node644",
"@target": "node646"
}
},
"node649": {
"edge647": {
"@length": 310.38,
"@source": "node649",
"@target": "node650"
},
"edge668": {
"@length": 432.3942,
"@source": "node649",
"@target": "node671"
}
},
"node650": {
"edge648": {
"@length": 60.5251,
"@source": "node650",
"@target": "node651"
},
"edge667": {
"@length": 3120.2444,
"@source": "node650",
"@target": "node670"
}
},
"node651": {
"edge649": {
"@length": 65.825,
"@source": "node651",
"@target": "node652"
},
"edge666": {
"@length": 3059.7193,
"@source": "node651",
"@target": "node669"
}
},
"node652": {
"edge650": {
"@length": 85.3798,
"@source": "node652",
"@target": "node653"
},
"edge665": {
"@length": 2993.8943,
"@source": "node652",
"@target": "node668"
}
},
"node653": {
"edge651": {
"@length": 2908.5145,
"@source": "node653",
"@target": "node654"
},
"edge652": {
"@length": 290.6219,
"@source": "node653",
"@target": "node655"
}
},
"node655": {
"edge653": {
"@length": 2617.8926,
"@source": "node655",
"@target": "node656"
},
"edge654": {
"@length": 545.4207,
"@source": "node655",
"@target": "node657"
}
},
"node657": {
"edge655": {
"@length": 2072.4719,
"@source": "node657",
"@target": "node658"
},
"edge656": {
"@length": 239.5535,
"@source": "node657",
"@target": "node659"
}
},
"node659": {
"edge657": {
"@length": 1832.9184,
"@source": "node659",
"@target": "node660"
},
"edge658": {
"@length": 612.6196,
"@source": "node659",
"@target": "node661"
}
},
"node661": {
"edge659": {
"@length": 768.8634,
"@source": "node661",
"@target": "node662"
},
"edge662": {
"@length": 484.7242,
"@source": "node661",
"@target": "node665"
}
},
"node662": {
"edge660": {
"@length": 451.4354,
"@source": "node662",
"@target": "node663"
},
"edge661": {
"@length": 451.4354,
"@source": "node662",
"@target": "node664"
}
},
"node665": {
"edge663": {
"@length": 735.5746,
"@source": "node665",
"@target": "node666"
},
"edge664": {
"@length": 735.5746,
"@source": "node665",
"@target": "node667"
}
},
"node671": {
"edge669": {
"@length": 92.8211,
"@source": "node671",
"@target": "node672"
},
"edge674": {
"@length": 2998.2303,
"@source": "node671",
"@target": "node677"
}
},
"node672": {
"edge670": {
"@length": 2905.4091,
"@source": "node672",
"@target": "node673"
},
"edge671": {
"@length": 75.4801,
"@source": "node672",
"@target": "node674"
}
},
"node674": {
"edge672": {
"@length": 2829.9291,
"@source": "node674",
"@target": "node675"
},
"edge673": {
"@length": 2829.9291,
"@source": "node674",
"@target": "node676"
}
},
"node678": {
"edge676": {
"@length": 11.1624,
"@source": "node678",
"@target": "node679"
},
"edge797": {
"@length": 476.3871,
"@source": "node678",
"@target": "node800"
}
},
"node679": {
"edge677": {
"@length": 44.037,
"@source": "node679",
"@target": "node680"
},
"edge792": {
"@length": 1749.0239,
"@source": "node679",
"@target": "node795"
}
},
"node680": {
"edge678": {
"@length": 97.3803,
"@source": "node680",
"@target": "node681"
},
"edge741": {
"@length": 59.0279,
"@source": "node680",
"@target": "node744"
}
},
"node681": {
"edge679": {
"@length": 56.4357,
"@source": "node681",
"@target": "node682"
},
"edge734": {
"@length": 89.7559,
"@source": "node681",
"@target": "node737"
}
},
"node682": {
"edge680": {
"@length": 75.7152,
"@source": "node682",
"@target": "node683"
},
"edge725": {
"@length": 309.6875,
"@source": "node682",
"@target": "node728"
}
},
"node683": {
"edge681": {
"@length": 74.5432,
"@source": "node683",
"@target": "node684"
},
"edge724": {
"@length": 3215.6672,
"@source": "node683",
"@target": "node727"
}
},
"node684": {
"edge682": {
"@length": 210.9458,
"@source": "node684",
"@target": "node685"
},
"edge715": {
"@length": 183.3507,
"@source": "node684",
"@target": "node718"
}
},
"node685": {
"edge683": {
"@length": 275.1354,
"@source": "node685",
"@target": "node686"
},
"edge694": {
"@length": 337.3879,
"@source": "node685",
"@target": "node697"
}
},
"node686": {
"edge684": {
"@length": 2655.0428,
"@source": "node686",
"@target": "node687"
},
"edge685": {
"@length": 850.505,
"@source": "node686",
"@target": "node688"
}
},
"node688": {
"edge686": {
"@length": 388.7473,
"@source": "node688",
"@target": "node689"
},
"edge689": {
"@length": 304.9567,
"@source": "node688",
"@target": "node692"
}
},
"node689": {
"edge687": {
"@length": 1415.7903,
"@source": "node689",
"@target": "node690"
},
"edge688": {
"@length": 1415.7903,
"@source": "node689",
"@target": "node691"
}
},
"node692": {
"edge690": {
"@length": 483.6783,
"@source": "node692",
"@target": "node693"
},
"edge693": {
"@length": 1499.5809,
"@source": "node692",
"@target": "node696"
}
},
"node693": {
"edge691": {
"@length": 1015.9026,
"@source": "node693",
"@target": "node694"
},
"edge692": {
"@length": 1015.9026,
"@source": "node693",
"@target": "node695"
}
},
"node697": {
"edge695": {
"@length": 2592.7903,
"@source": "node697",
"@target": "node698"
},
"edge696": {
"@length": 521.7337,
"@source": "node697",
"@target": "node699"
}
},
"node699": {
"edge697": {
"@length": 198.804,
"@source": "node699",
"@target": "node700"
},
"edge712": {
"@length": 507.711,
"@source": "node699",
"@target": "node715"
}
},
"node700": {
"edge698": {
"@length": 83.2138,
"@source": "node700",
"@target": "node701"
},
"edge709": {
"@length": 178.9753,
"@source": "node700",
"@target": "node712"
}
},
"node701": {
"edge699": {
"@length": 486.1553,
"@source": "node701",
"@target": "node702"
},
"edge704": {
"@length": 236.6806,
"@source": "node701",
"@target": "node707"
}
},
"node702": {
"edge700": {
"@length": 1302.8835,
"@source": "node702",
"@target": "node703"
},
"edge701": {
"@length": 901.1743,
"@source": "node702",
"@target": "node704"
}
},
"node704": {
"edge702": {
"@length": 401.7092,
"@source": "node704",
"@target": "node705"
},
"edge703": {
"@length": 401.7092,
"@source": "node704",
"@target": "node706"
}
},
"node707": {
"edge705": {
"@length": 973.4897,
"@source": "node707",
"@target": "node708"
},
"edge708": {
"@length": 1552.3583,
"@source": "node707",
"@target": "node711"
}
},
"node708": {
"edge706": {
"@length": 578.8686,
"@source": "node708",
"@target": "node709"
},
"edge707": {
"@length": 578.8686,
"@source": "node708",
"@target": "node710"
}
},
"node712": {
"edge710": {
"@length": 1693.2773,
"@source": "node712",
"@target": "node713"
},
"edge711": {
"@length": 1693.2773,
"@source": "node712",
"@target": "node714"
}
},
"node715": {
"edge713": {
"@length": 1563.3456,
"@source": "node715",
"@target": "node716"
},
"edge714": {
"@length": 1563.3456,
"@source": "node715",
"@target": "node717"
}
},
"node718": {
"edge716": {
"@length": 130.768,
"@source": "node718",
"@target": "node719"
},
"edge723": {
"@length": 2957.7733,
"@source": "node718",
"@target": "node726"
}
},
"node719": {
"edge717": {
"@length": 106.8356,
"@source": "node719",
"@target": "node720"
},
"edge722": {
"@length": 2827.0053,
"@source": "node719",
"@target": "node725"
}
},
"node720": {
"edge718": {
"@length": 94.7777,
"@source": "node720",
"@target": "node721"
},
"edge721": {
"@length": 2720.1697,
"@source": "node720",
"@target": "node724"
}
},
"node721": {
"edge719": {
"@length": 2625.3921,
"@source": "node721",
"@target": "node722"
},
"edge720": {
"@length": 2625.3921,
"@source": "node721",
"@target": "node723"
}
},
"node728": {
"edge726": {
"@length": 132.6971,
"@source": "node728",
"@target": "node729"
},
"edge731": {
"@length": 301.8337,
"@source": "node728",
"@target": "node734"
}
},
"node729": {
"edge727": {
"@length": 2848.9978,
"@source": "node729",
"@target": "node730"
},
"edge728": {
"@length": 142.335,
"@source": "node729",
"@target": "node731"
}
},
"node731": {
"edge729": {
"@length": 2706.6628,
"@source": "node731",
"@target": "node732"
},
"edge730": {
"@length": 2706.6628,
"@source": "node731",
"@target": "node733"
}
},
"node734": {
"edge732": {
"@length": 2679.8612,
"@source": "node734",
"@target": "node735"
},
"edge733": {
"@length": 2679.8612,
"@source": "node734",
"@target": "node736"
}
},
"node737": {
"edge735": {
"@length": 224.5933,
"@source": "node737",
"@target": "node738"
},
"edge740": {
"@length": 3258.0622,
"@source": "node737",
"@target": "node743"
}
},
"node738": {
"edge736": {
"@length": 317.0106,
"@source": "node738",
"@target": "node739"
},
"edge739": {
"@length": 3033.4689,
"@source": "node738",
"@target": "node742"
}
},
"node739": {
"edge737": {
"@length": 2716.4582,
"@source": "node739",
"@target": "node740"
},
"edge738": {
"@length": 2716.4582,
"@source": "node739",
"@target": "node741"
}
},
"node744": {
"edge742": {
"@length": 81.0981,
"@source": "node744",
"@target": "node745"
},
"edge773": {
"@length": 145.2153,
"@source": "node744",
"@target": "node776"
}
},
"node745": {
"edge743": {
"@length": 57.3794,
"@source": "node745",
"@target": "node746"
},
"edge772": {
"@length": 3305.0723,
"@source": "node745",
"@target": "node775"
}
},
"node746": {
"edge744": {
"@length": 346.7993,
"@source": "node746",
"@target": "node747"
},
"edge761": {
"@length": 82.6824,
"@source": "node746",
"@target": "node764"
}
},
"node747": {
"edge745": {
"@length": 153.6471,
"@source": "node747",
"@target": "node748"
},
"edge756": {
"@length": 302.767,
"@source": "node747",
"@target": "node759"
}
},
"node748": {
"edge746": {
"@length": 36.5905,
"@source": "node748",
"@target": "node749"
},
"edge753": {
"@length": 168.7343,
"@source": "node748",
"@target": "node756"
}
},
"node749": {
"edge747": {
"@length": 448.28,
"@source": "node749",
"@target": "node750"
},
"edge752": {
"@length": 2710.6561,
"@source": "node749",
"@target": "node755"
}
},
"node750": {
"edge748": {
"@length": 539.2491,
"@source": "node750",
"@target": "node751"
},
"edge751": {
"@length": 2262.3761,
"@source": "node750",
"@target": "node754"
}
},
"node751": {
"edge749": {
"@length": 1723.127,
"@source": "node751",
"@target": "node752"
},
"edge750": {
"@length": 1723.127,
"@source": "node751",
"@target": "node753"
}
},
"node756": {
"edge754": {
"@length": 2578.5122,
"@source": "node756",
"@target": "node757"
},
"edge755": {
"@length": 2578.5122,
"@source": "node756",
"@target": "node758"
}
},
"node759": {
"edge757": {
"@length": 406.071,
"@source": "node759",
"@target": "node760"
},
"edge760": {
"@length": 2598.1267,
"@source": "node759",
"@target": "node763"
}
},
"node760": {
"edge758": {
"@length": 2192.0557,
"@source": "node760",
"@target": "node761"
},
"edge759": {
"@length": 2192.0557,
"@source": "node760",
"@target": "node762"
}
},
"node764": {
"edge762": {
"@length": 484.3465,
"@source": "node764",
"@target": "node765"
},
"edge767": {
"@length": 1837.0723,
"@source": "node764",
"@target": "node770"
}
},
"node765": {
"edge763": {
"@length": 351.0339,
"@source": "node765",
"@target": "node766"
},
"edge766": {
"@length": 2680.664,
"@source": "node765",
"@target": "node769"
}
},
"node766": {
"edge764": {
"@length": 2329.63,
"@source": "node766",
"@target": "node767"
},
"edge765": {
"@length": 2329.63,
"@source": "node766",
"@target": "node768"
}
},
"node770": {
"edge768": {
"@length": 1327.9382,
"@source": "node770",
"@target": "node771"
},
"edge769": {
"@length": 72.7173,
"@source": "node770",
"@target": "node772"
}
},
"node772": {
"edge770": {
"@length": 1255.2209,
"@source": "node772",
"@target": "node773"
},
"edge771": {
"@length": 1255.2209,
"@source": "node772",
"@target": "node774"
}
},
"node776": {
"edge774": {
"@length": 149.0918,
"@source": "node776",
"@target": "node777"
},
"edge789": {
"@length": 826.2384,
"@source": "node776",
"@target": "node792"
}
},
"node777": {
"edge775": {
"@length": 186.6188,
"@source": "node777",
"@target": "node778"
},
"edge784": {
"@length": 310.0364,
"@source": "node777",
"@target": "node787"
}
},
"node778": {
"edge776": {
"@length": 421.7676,
"@source": "node778",
"@target": "node779"
},
"edge783": {
"@length": 2905.2445,
"@source": "node778",
"@target": "node786"
}
},
"node779": {
"edge777": {
"@length": 2483.4769,
"@source": "node779",
"@target": "node780"
},
"edge778": {
"@length": 167.4489,
"@source": "node779",
"@target": "node781"
}
},
"node781": {
"edge779": {
"@length": 2316.028,
"@source": "node781",
"@target": "node782"
},
"edge780": {
"@length": 1936.9357,
"@source": "node781",
"@target": "node783"
}
},
"node783": {
"edge781": {
"@length": 379.0923,
"@source": "node783",
"@target": "node784"
},
"edge782": {
"@length": 379.0923,
"@source": "node783",
"@target": "node785"
}
},
"node787": {
"edge785": {
"@length": 2781.8269,
"@source": "node787",
"@target": "node788"
},
"edge786": {
"@length": 148.6657,
"@source": "node787",
"@target": "node789"
}
},
"node789": {
"edge787": {
"@length": 2633.1612,
"@source": "node789",
"@target": "node790"
},
"edge788": {
"@length": 2633.1612,
"@source": "node789",
"@target": "node791"
}
},
"node792": {
"edge790": {
"@length": 2414.7168,
"@source": "node792",
"@target": "node793"
},
"edge791": {
"@length": 2414.7168,
"@source": "node792",
"@target": "node794"
}
},
"node795": {
"edge793": {
"@length": 1740.2115,
"@source": "node795",
"@target": "node796"
},
"edge794": {
"@length": 957.7602,
"@source": "node795",
"@target": "node797"
}
},
"node797": {
"edge795": {
"@length": 782.4512,
"@source": "node797",
"@target": "node798"
},
"edge796": {
"@length": 782.4512,
"@source": "node797",
"@target": "node799"
}
},
"node800": {
"edge798": {
"@length": 3024.0106,
"@source": "node800",
"@target": "node801"
},
"edge799": {
"@length": 92.002,
"@source": "node800",
"@target": "node802"
}
},
"node802": {
"edge800": {
"@length": 132.6386,
"@source": "node802",
"@target": "node803"
},
"edge817": {
"@length": 185.9619,
"@source": "node802",
"@target": "node820"
}
},
"node803": {
"edge801": {
"@length": 517.3949,
"@source": "node803",
"@target": "node804"
},
"edge816": {
"@length": 2799.3701,
"@source": "node803",
"@target": "node819"
}
},
"node804": {
"edge802": {
"@length": 2281.9751,
"@source": "node804",
"@target": "node805"
},
"edge803": {
"@length": 412.819,
"@source": "node804",
"@target": "node806"
}
},
"node806": {
"edge804": {
"@length": 625.2843,
"@source": "node806",
"@target": "node807"
},
"edge815": {
"@length": 1869.1562,
"@source": "node806",
"@target": "node818"
}
},
"node807": {
"edge805": {
"@length": 673.2762,
"@source": "node807",
"@target": "node808"
},
"edge808": {
"@length": 336.6193,
"@source": "node807",
"@target": "node811"
}
},
"node808": {
"edge806": {
"@length": 570.5957,
"@source": "node808",
"@target": "node809"
},
"edge807": {
"@length": 570.5957,
"@source": "node808",
"@target": "node810"
}
},
"node811": {
"edge809": {
"@length": 393.6579,
"@source": "node811",
"@target": "node812"
},
"edge812": {
"@length": 338.8258,
"@source": "node811",
"@target": "node815"
}
},
"node812": {
"edge810": {
"@length": 513.5946,
"@source": "node812",
"@target": "node813"
},
"edge811": {
"@length": 513.5946,
"@source": "node812",
"@target": "node814"
}
},
"node815": {
"edge813": {
"@length": 568.4268,
"@source": "node815",
"@target": "node816"
},
"edge814": {
"@length": 568.4268,
"@source": "node815",
"@target": "node817"
}
},
"node820": {
"edge818": {
"@length": 2746.0468,
"@source": "node820",
"@target": "node821"
},
"edge819": {
"@length": 2746.0468,
"@source": "node820",
"@target": "node822"
}
},
"node823": {
"edge821": {
"@length": 179.8606,
"@source": "node823",
"@target": "node824"
},
"edge824": {
"@length": 185.9116,
"@source": "node823",
"@target": "node827"
}
},
"node824": {
"edge822": {
"@length": 3388.828,
"@source": "node824",
"@target": "node825"
},
"edge823": {
"@length": 3388.828,
"@source": "node824",
"@target": "node826"
}
},
"node827": {
"edge825": {
"@length": 3382.777,
"@source": "node827",
"@target": "node828"
},
"edge826": {
"@length": 3382.777,
"@source": "node827",
"@target": "node829"
}
}
},
"nodeById": {
"node593": {
"@label": "3188.33-4179.37",
"@root": true
},
"node594": {
"@label": "3167.25-4138.7"
},
"node595": {
"@label": "3116.25-4080.15"
},
"node596": {
"@label": "3062.91-3993.52"
},
"node597": {
"@label": "2694.17-3501.26"
},
"node598": {
"@otu": "otu3"
},
"node599": {
"@label": "2153.6-2753.86"
},
"node600": {
"@label": "1730.19-2093.03"
},
"node601": {
"@label": "1600.01-1875.91"
},
"node602": {
"@otu": "otu4"
},
"node603": {
"@otu": "otu5"
},
"node604": {
"@otu": "otu6"
},
"node605": {
"@otu": "otu7"
},
"node606": {
"@label": "2455.13-3474.44"
},
"node607": {
"@otu": "otu8"
},
"node608": {
"@otu": "otu9"
},
"node609": {
"@label": "3081.86-4030.0"
},
"node610": {
"@label": "3035.68-3966.07"
},
"node611": {
"@label": "2935.38-3849.94"
},
"node612": {
"@label": "2462.22-3324.9"
},
"node613": {
"@label": "2228.8-3181.81"
},
"node614": {
"@otu": "otu10"
},
"node615": {
"@otu": "otu11"
},
"node616": {
"@otu": "otu12"
},
"node617": {
"@label": "2606.41-3534.98"
},
"node618": {
"@otu": "otu13"
},
"node619": {
"@otu": "otu14"
},
"node620": {
"@label": "2842.79-3744.11"
},
"node621": {
"@label": "2525.15-3414.75"
},
"node622": {
"@label": "2423.92-3310.6"
},
"node623": {
"@label": "1810.87-2901.73"
},
"node624": {
"@otu": "otu15"
},
"node625": {
"@otu": "otu16"
},
"node626": {
"@otu": "otu167"
},
"node627": {
"@otu": "otu18"
},
"node628": {
"@label": "2612.27-3487.98"
},
"node629": {
"@label": "2415.97-3291.68"
},
"node630": {
"@label": "2365.8-3242.3"
},
"node631": {
"@label": "2137.73-3051.32"
},
"node632": {
"@label": "1770.91-2782.88"
},
"node633": {
"@otu": "otu19"
},
"node634": {
"@otu": "otu20"
},
"node635": {
"@label": "1914.68-2869.37"
},
"node636": {
"@otu": "otu21"
},
"node637": {
"@otu": "otu22"
},
"node638": {
"@otu": "otu23"
},
"node639": {
"@otu": "otu24"
},
"node640": {
"@label": "2418.27-3332.43"
},
"node641": {
"@label": "2323.01-3236.81"
},
"node642": {
"@label": "1926.46-2910.88"
},
"node643": {
"@otu": "otu25"
},
"node644": {
"@label": "1806.94-2796.5"
},
"node645": {
"@otu": "otu26"
},
"node646": {
"@otu": "otu27"
},
"node647": {
"@otu": "otu28"
},
"node648": {
"@otu": "otu29"
},
"node649": {
"@label": "2994.27-3919.37"
},
"node650": {
"@label": "2725.46-3609.27"
},
"node651": {
"@label": "2649.02-3526.87"
},
"node652": {
"@label": "2594.15-3470.07"
},
"node653": {
"@label": "2505.19-3386.93"
},
"node654": {
"@otu": "otu30"
},
"node655": {
"@label": "2219.3-3096.08"
},
"node656": {
"@otu": "otu31"
},
"node657": {
"@label": "1643.03-2573.05"
},
"node658": {
"@otu": "otu32"
},
"node659": {
"@label": "1398.99-2272.33"
},
"node660": {
"@otu": "otu33"
},
"node661": {
"@label": "914.626-1613.12"
},
"node662": {
"@label": "335.083-512.455"
},
"node663": {
"@otu": "otu184"
},
"node664": {
"@otu": "otu185"
},
"node665": {
"@label": "500.388-1055.73"
},
"node666": {
"@otu": "otu186"
},
"node667": {
"@otu": "otu187"
},
"node668": {
"@otu": "otu38"
},
"node669": {
"@otu": "otu39"
},
"node670": {
"@otu": "otu40"
},
"node671": {
"@label": "2537.95-3458.46"
},
"node672": {
"@label": "2457.68-3386.89"
},
"node673": {
"@otu": "otu41"
},
"node674": {
"@label": "2384.29-3299.39"
},
"node675": {
"@otu": "otu42"
},
"node676": {
"@otu": "otu43"
},
"node677": {
"@otu": "otu44"
},
"node678": {
"@label": "3053.22-3983.55"
},
"node679": {
"@label": "3046.71-3972.43"
},
"node680": {
"@label": "3015.99-3920.9"
},
"node681": {
"@label": "2928.4-3809.08"
},
"node682": {
"@label": "2889.44-3751.64"
},
"node683": {
"@label": "2828.61-3656.86"
},
"node684": {
"@label": "2763.69-3556.2"
},
"node685": {
"@label": "2595.21-3289.67"
},
"node686": {
"@label": "2355.15-2955.59"
},
"node687": {
"@otu": "otu45"
},
"node688": {
"@label": "1658.77-1950.61"
},
"node689": {
"@label": "1257.92-1594.86"
},
"node690": {
"@otu": "otu196"
},
"node691": {
"@otu": "otu197"
},
"node692": {
"@label": "1357.0-1627.48"
},
"node693": {
"@label": "823.753-1102.51"
},
"node694": {
"@otu": "otu198"
},
"node695": {
"@otu": "otu199"
},
"node696": {
"@otu": "otu200"
},
"node697": {
"@label": "2320.29-2873.17"
},
"node698": {
"@otu": "otu80"
},
"node699": {
"@label": "1926.3-2247.56"
},
"node700": {
"@label": "1772.68-1997.89"
},
"node701": {
"@label": "1690.56-1904.07"
},
"node702": {
"@label": "1033.64-1437.34"
},
"node703": {
"@otu": "otu81"
},
"node704": {
"@label": "267.209-501.524"
},
"node705": {
"@otu": "otu232"
},
"node706": {
"@otu": "otu233"
},
"node707": {
"@label": "1440.72-1635.94"
},
"node708": {
"@label": "346.873-775.807"
},
"node709": {
"@otu": "otu234"
},
"node710": {
"@otu": "otu235"
},
"node711": {
"@otu": "otu236"
},
"node712": {
"@label": "1640.06-1783.63"
},
"node713": {
"@otu": "otu87"
},
"node714": {
"@otu": "otu88"
},
"node715": {
"@label": "1295.15-1823.71"
},
"node716": {
"@otu": "otu89"
},
"node717": {
"@otu": "otu90"
},
"node718": {
"@label": "2601.12-3321.73"
},
"node719": {
"@label": "2484.58-3184.56"
},
"node720": {
"@label": "2396.5-3077.4"
},
"node721": {
"@label": "2286.84-2979.69"
},
"node722": {
"@otu": "otu91"
},
"node723": {
"@otu": "otu92"
},
"node724": {
"@otu": "otu93"
},
"node725": {
"@otu": "otu94"
},
"node726": {
"@otu": "otu95"
},
"node727": {
"@otu": "otu96"
},
"node728": {
"@label": "2601.64-3409.58"
},
"node729": {
"@label": "2466.41-3266.52"
},
"node730": {
"@otu": "otu97"
},
"node731": {
"@label": "2293.87-3099.25"
},
"node732": {
"@otu": "otu98"
},
"node733": {
"@otu": "otu99"
},
"node734": {
"@label": "2271.96-3088.32"
},
"node735": {
"@otu": "otu100"
},
"node736": {
"@otu": "otu101"
},
"node737": {
"@label": "2847.44-3712.52"
},
"node738": {
"@label": "2598.37-3455.9"
},
"node739": {
"@label": "2315.34-3169.69"
},
"node740": {
"@otu": "otu102"
},
"node741": {
"@otu": "otu103"
},
"node742": {
"@otu": "otu104"
},
"node743": {
"@otu": "otu105"
},
"node744": {
"@label": "2957.94-3845.41"
},
"node745": {
"@label": "2899.35-3762.73"
},
"node746": {
"@label": "2828.01-3683.91"
},
"node747": {
"@label": "2521.47-3339.86"
},
"node748": {
"@label": "2367.55-3159.91"
},
"node749": {
"@label": "2348.71-3147.13"
},
"node750": {
"@label": "1880.24-2765.1"
},
"node751": {
"@label": "1301.09-2213.11"
},
"node752": {
"@otu": "otu106"
},
"node753": {
"@otu": "otu107"
},
"node754": {
"@otu": "otu108"
},
"node755": {
"@otu": "otu109"
},
"node756": {
"@label": "2197.42-3001.89"
},
"node757": {
"@otu": "otu260"
},
"node758": {
"@otu": "otu111"
},
"node759": {
"@label": "2245.23-3035.5"
},
"node760": {
"@label": "1327.06-2901.83"
},
"node761": {
"@otu": "otu112"
},
"node762": {
"@otu": "otu113"
},
"node763": {
"@otu": "otu264"
},
"node764": {
"@label": "2724.85-3579.54"
},
"node765": {
"@label": "2213.37-3111.67"
},
"node766": {
"@label": "1812.58-2850.45"
},
"node767": {
"@otu": "otu115"
},
"node768": {
"@otu": "otu116"
},
"node769": {
"@otu": "otu117"
},
"node770": {
"@label": "837.226-1625.23"
},
"node771": {
"@otu": "otu118"
},
"node772": {
"@label": "772.626-1576.14"
},
"node773": {
"@otu": "otu269"
},
"node774": {
"@otu": "otu270"
},
"node775": {
"@otu": "otu121"
},
"node776": {
"@label": "2835.72-3691.17"
},
"node777": {
"@label": "2713.17-3525.15"
},
"node778": {
"@label": "2533.14-3301.1"
},
"node779": {
"@label": "2159.65-2838.44"
},
"node780": {
"@otu": "otu122"
},
"node781": {
"@label": "1986.13-2659.56"
},
"node782": {
"@otu": "otu123"
},
"node783": {
"@label": "217.968-511.156"
},
"node784": {
"@otu": "otu274"
},
"node785": {
"@otu": "otu275"
},
"node786": {
"@otu": "otu126"
},
"node787": {
"@label": "2408.25-3177.09"
},
"node788": {
"@otu": "otu127"
},
"node789": {
"@label": "2254.9-3051.45"
},
"node790": {
"@otu": "otu128"
},
"node791": {
"@otu": "otu129"
},
"node792": {
"@label": "1013.63-3365.6"
},
"node793": {
"@otu": "otu130"
},
"node794": {
"@otu": "otu131"
},
"node795": {
"@label": "1028.02-2426.5"
},
"node796": {
"@otu": "otu132"
},
"node797": {
"@label": "464.472-1071.53"
},
"node798": {
"@otu": "otu283"
},
"node799": {
"@otu": "otu284"
},
"node800": {
"@label": "2643.84-3498.98"
},
"node801": {
"@otu": "otu135"
},
"node802": {
"@label": "2523.17-3372.3"
},
"node803": {
"@label": "2401.46-3257.95"
},
"node804": {
"@label": "1819.75-2723.57"
},
"node805": {
"@otu": "otu136"
},
"node806": {
"@label": "1422.33-2298.25"
},
"node807": {
"@label": "835.028-1560.23"
},
"node808": {
"@label": "344.061-858.664"
},
"node809": {
"@otu": "otu287"
},
"node810": {
"@otu": "otu288"
},
"node811": {
"@label": "578.159-1149.08"
},
"node812": {
"@label": "306.769-715.211"
},
"node813": {
"@otu": "otu289"
},
"node814": {
"@otu": "otu290"
},
"node815": {
"@label": "322.517-753.621"
},
"node816": {
"@otu": "otu291"
},
"node817": {
"@otu": "otu292"
},
"node818": {
"@otu": "otu143"
},
"node819": {
"@otu": "otu144"
},
"node820": {
"@label": "2343.29-3190.11"
},
"node821": {
"@otu": "otu145"
},
"node822": {
"@otu": "otu146"
},
"node823": {
"@label": "3120.23-4102.96"
},
"node824": {
"@label": "2945.11-3911.05"
},
"node825": {
"@otu": "otu147"
},
"node826": {
"@otu": "otu148"
},
"node827": {
"@label": "2898.99-3862.31"
},
"node828": {
"@otu": "otu149"
},
"node829": {
"@otu": "otu150"
}
}
}
}
}
}
}
}
