{
"nexml": {
"@about": "#study",
"@generator": "Open Tree API",
"@id": "study",
"@nexml2json": "1.2.1",
"@nexmljson": "http://purl.org/opentree/nexson",
"@version": "0.9",
"@xmlns": {
"$": "http://www.nexml.org/2009",
"nex": "http://www.nexml.org/2009",
"ot": "http://purl.org/opentree-terms#",
"xhtml": "http://www.w3.org/1999/xhtml/vocab#",
"xsd": "http://www.w3.org/2001/XMLSchema#",
"xsi": "http://www.w3.org/2001/XMLSchema-instance"
},
"^ot:agents": {
"agent": [
{
"@description": "Open Tree NexSON validation",
"@id": "peyotl-validator",
"@name": "api.opentreeoflife.org/validate",
"@url": "https://github.com/OpenTreeOfLife/peyotl",
"@version": "0.0.4a",
"invocation": {
"commandLine": [],
"otherProperty": [
{
"name": "pythonVersion",
"value": "3.10.12"
},
{
"name": "pythonImplementation",
"value": "CPython"
}
]
}
},
{
"@description": "Web-based interface for submitting, editing, and reviewing studies in the Open Tree of Life project.",
"@id": "opentree-curation-webapp",
"@name": "OpenTree curation webapp",
"@url": "https://github.com/OpenTreeOfLife/opentree",
"@version": "0.0.0"
}
]
},
"^ot:annotationEvents": {
"annotation": [
{
"@dateCreated": "2025-03-03T10:57:35.267Z",
"@description": "Aids for mapping study OTUs to OTT taxa",
"@id": "otu-mapping-hints",
"@passedChecks": true,
"@preserve": true,
"@wasAssociatedWithAgentId": "opentree-curation-webapp",
"message": [
{
"@code": "OTU_MAPPING_HINTS",
"@humanMessageType": "NONE",
"@severity": "INFO",
"data": {
"autoAcceptExactMatches": true,
"searchContext": {
"$": "Insects"
},
"substitutions": {
"substitution": [
{
"@active": false,
"@valid": true,
"new": {
"$": ""
},
"old": {
"$": ""
}
}
]
},
"useFuzzyMatching": false
},
"refersTo": {
"@top": {
"$": "meta"
}
}
}
]
},
{
"@dateCreated": "2025-03-03T10:57:35.267Z",
"@description": "Describes external namesets merged into this study",
"@id": "merged-namesets-metadata",
"@passedChecks": true,
"@preserve": true,
"@wasAssociatedWithAgentId": "opentree-curation-webapp",
"message": [
{
"@code": "MERGED_NAMESET_INFO",
"@humanMessageType": "NONE",
"@severity": "INFO",
"data": {
"namesets": {
"nameset": []
}
},
"refersTo": {
"@top": {
"$": "meta"
}
}
}
]
},
{
"@dateCreated": "2025-03-03T10:57:35.267Z",
"@description": "Describes supporting data files for this study",
"@id": "supporting-files-metadata",
"@passedChecks": true,
"@preserve": true,
"@wasAssociatedWithAgentId": "opentree-curation-webapp",
"message": [
{
"@code": "SUPPORTING_FILE_INFO",
"@humanMessageType": "NONE",
"@severity": "INFO",
"data": {
"@movedToPermanentArchive": false,
"files": {
"file": [
{
"@filename": "Condamine2012Troidini.nwk",
"@size": 620,
"@type": "newick",
"@url": "/curator/download/supporting_files.doc.b22605738617cbb0.436f6e64616d696e653230313254726f6964696e692e6e776b.nwk",
"description": {
"$": "Source data for tree(s) 'tree1'"
},
"sourceForTree": [
{
"$": "tree1"
}
]
},
{
"@filename": "image.png",
"@size": 543,
"@type": "",
"@url": "/curator/supporting_files/download/supporting_files.doc.8071c95f26377034.696d6167652e706e67.png",
"description": {
"$": ""
},
"sourceForTree": []
},
{
"@filename": "image.png",
"@size": 660,
"@type": "",
"@url": "/curator/supporting_files/download/supporting_files.doc.8841397b23f33e41.696d6167652e706e67.png",
"description": {
"$": ""
},
"sourceForTree": []
},
{
"@filename": "image.png",
"@size": 866,
"@type": "",
"@url": "/curator/supporting_files/download/supporting_files.doc.915d0080ff4329c0.696d6167652e706e67.png",
"description": {
"$": ""
},
"sourceForTree": []
},
{
"@filename": "image.png",
"@size": 620,
"@type": "",
"@url": "/curator/supporting_files/download/supporting_files.doc.ab0230a59e8efa42.696d6167652e706e67.png",
"description": {
"$": ""
},
"sourceForTree": []
},
{
"@filename": "image.png",
"@size": 1748,
"@type": "",
"@url": "/curator/supporting_files/download/supporting_files.doc.bff271e854fdc67f.696d6167652e706e67.png",
"description": {
"$": ""
},
"sourceForTree": []
},
{
"@filename": "image.png",
"@size": 1804,
"@type": "",
"@url": "/curator/supporting_files/download/supporting_files.doc.810e638c3ce006b4.696d6167652e706e67.png",
"description": {
"$": ""
},
"sourceForTree": []
},
{
"@filename": "image.png",
"@size": 3753,
"@type": "",
"@url": "/curator/supporting_files/download/supporting_files.doc.b73eb5588f930b4c.696d6167652e706e67.png",
"description": {
"$": ""
},
"sourceForTree": []
}
]
}
},
"refersTo": {
"@top": {
"$": "meta"
}
}
}
]
}
]
},
"^ot:candidateTreeForSynthesis": [],
"^ot:comment": "",
"^ot:curatorName": [
"dchesters"
],
"^ot:dataDeposit": {
"@href": "https://bmcecolevol.biomedcentral.com/articles/10.1186/1471-2148-12-82#additional-information"
},
"^ot:focalClade": 951458,
"^ot:focalCladeOTTTaxonName": "Troidini",
"^ot:otusElementOrder": [
"otus1"
],
"^ot:studyId": "ot_2588",
"^ot:studyPublication": {
"@href": "https://doi.org/10.1186/1471-2148-12-82"
},
"^ot:studyPublicationReference": "Condamine, F. L., Silva-Brand\u00e3o, K. L., Kergoat, G. J., & Sperling, F. A. (2012). Biogeographic and diversification patterns of Neotropical Troidini butterflies (Papilionidae) support a museum model of diversity dynamics for Amazonia. BMC Evolutionary Biology, 12(1), 82. https://doi.org/10.1186/1471-2148-12-82\n",
"^ot:studyYear": 2012,
"^ot:tag": [],
"^ot:treesElementOrder": [
"trees1"
],
"^xhtml:license": {
"@href": "https://creativecommons.org/licenses/by/3.0/",
"@name": "CC-BY 3.0"
},
"highestMintedElementIDs": {
"agent": 0,
"annotation": 0,
"edge": 62,
"message": 0,
"node": 63,
"otu": 32,
"otus": 2,
"tree": 1,
"trees": 2
},
"otusById": {
"otus1": {
"otuById": {
"otu1": {
"^ot:originalLabel": "Graphium agamemnon",
"^ot:ottId": 725028,
"^ot:ottTaxonName": "Graphium agamemnon"
},
"otu10": {
"^ot:originalLabel": "Euryades duponchelii",
"^ot:ottId": 36582,
"^ot:ottTaxonName": "Euryades duponchelii"
},
"otu11": {
"^ot:originalLabel": "Parides ascanius",
"^ot:ottId": 589542,
"^ot:ottTaxonName": "Parides ascanius"
},
"otu12": {
"^ot:originalLabel": "Parides bunichus",
"^ot:ottId": 589545,
"^ot:ottTaxonName": "Parides bunichus"
},
"otu13": {
"^ot:originalLabel": "Parides agavus",
"^ot:ottId": 589540,
"^ot:ottTaxonName": "Parides agavus"
},
"otu14": {
"^ot:originalLabel": "Parides proneus",
"^ot:ottId": 16777,
"^ot:ottTaxonName": "Parides proneus"
},
"otu15": {
"^ot:originalLabel": "Parides aeneas",
"^ot:ottId": 589538,
"^ot:ottTaxonName": "Parides aeneas"
},
"otu16": {
"^ot:originalLabel": "Parides tros",
"^ot:ottId": 16780,
"^ot:ottTaxonName": "Parides tros"
},
"otu17": {
"^ot:originalLabel": "Parides lysander",
"^ot:ottId": 983864,
"^ot:ottTaxonName": "Parides lysander"
},
"otu18": {
"^ot:originalLabel": "Parides burchellanus",
"^ot:ottId": 653801,
"^ot:ottTaxonName": "Parides burchellanus"
},
"otu19": {
"^ot:originalLabel": "Parides panthonus",
"^ot:ottId": 983875,
"^ot:ottTaxonName": "Parides panthonus"
},
"otu2": {
"^ot:originalLabel": "Papilio machaon",
"^ot:ottId": 1018322,
"^ot:ottTaxonName": "Papilio machaon"
},
"otu20": {
"^ot:originalLabel": "Parides ecbolius"
},
"otu21": {
"^ot:originalLabel": "Parides neophilus",
"^ot:ottId": 160806,
"^ot:ottTaxonName": "Parides neophilus"
},
"otu22": {
"^ot:originalLabel": "Parides eurimedes",
"^ot:ottId": 589534,
"^ot:ottTaxonName": "Parides eurimedes"
},
"otu23": {
"^ot:originalLabel": "Parides zacynthus",
"^ot:ottId": 101688,
"^ot:ottTaxonName": "Parides zacynthus"
},
"otu24": {
"^ot:originalLabel": "Parides chabrias",
"^ot:ottId": 589544,
"^ot:ottTaxonName": "Parides chabrias"
},
"otu25": {
"^ot:originalLabel": "Parides childrenae",
"^ot:ottId": 589536,
"^ot:ottTaxonName": "Parides childrenae"
},
"otu26": {
"^ot:originalLabel": "Parides sesostris",
"^ot:ottId": 16778,
"^ot:ottTaxonName": "Parides sesostris"
},
"otu27": {
"^ot:originalLabel": "Parides photinus",
"^ot:ottId": 725025,
"^ot:ottTaxonName": "Parides photinus"
},
"otu28": {
"^ot:originalLabel": "Parides panares",
"^ot:ottId": 826393,
"^ot:ottTaxonName": "Parides panares"
},
"otu29": {
"^ot:originalLabel": "Parides iphidamas",
"^ot:ottId": 858323,
"^ot:ottTaxonName": "Parides iphidamas"
},
"otu3": {
"^ot:originalLabel": "Teinopalpus imperialis",
"^ot:ottId": 803762,
"^ot:ottTaxonName": "Teinopalpus imperialis"
},
"otu30": {
"^ot:originalLabel": "Parides anchises",
"^ot:ottId": 589543,
"^ot:ottTaxonName": "Parides anchises"
},
"otu31": {
"^ot:originalLabel": "Parides erithalion",
"^ot:ottId": 858319,
"^ot:ottTaxonName": "Parides erithalion"
},
"otu32": {
"^ot:originalLabel": "Parides vertumnus",
"^ot:ottId": 16781,
"^ot:ottTaxonName": "Parides vertumnus"
},
"otu4": {
"^ot:originalLabel": "Battus philenor",
"^ot:ottId": 414404,
"^ot:ottTaxonName": "Battus philenor"
},
"otu5": {
"^ot:originalLabel": "Battus polydamas",
"^ot:ottId": 805571,
"^ot:ottTaxonName": "Battus polydamas"
},
"otu6": {
"^ot:originalLabel": "Battus polystictus",
"^ot:ottId": 589539,
"^ot:ottTaxonName": "Battus polystictus"
},
"otu7": {
"^ot:originalLabel": "Battus belus",
"^ot:ottId": 68548,
"^ot:ottTaxonName": "Battus belus"
},
"otu8": {
"^ot:originalLabel": "Battus crassus",
"^ot:ottId": 684020,
"^ot:ottTaxonName": "Battus crassus"
},
"otu9": {
"^ot:originalLabel": "Euryades corethrus",
"^ot:ottId": 684027,
"^ot:ottTaxonName": "Euryades corethrus"
}
}
}
},
"treesById": {
"trees1": {
"@otus": "otus1",
"^ot:treeElementOrder": [
"tree1"
],
"treeById": {
"tree1": {
"@label": "12862_2012_2075_MOESM3_ESM.txt, Fig. 1, BI",
"@xsi:type": "nex:FloatTree",
"^ot:branchLengthDescription": "",
"^ot:branchLengthMode": "ot:undefined",
"^ot:curatedType": "Bayesian inference ",
"^ot:inGroupClade": "node7",
"^ot:nodeLabelMode": "",
"^ot:nodeLabelTimeUnit": "",
"^ot:outGroupEdge": "",
"^ot:reasonsToExcludeFromSynthesis": [],
"^ot:rootNodeId": "node1",
"^ot:specifiedRoot": "node1",
"^ot:tag": [],
"^ot:unrootedTree": false,
"edgeBySourceId": {
"node1": {
"edge1": {
"@source": "node1",
"@target": "node2"
},
"edge2": {
"@source": "node1",
"@target": "node3"
}
},
"node12": {
"edge12": {
"@source": "node12",
"@target": "node13"
},
"edge13": {
"@source": "node12",
"@target": "node14"
}
},
"node14": {
"edge14": {
"@source": "node14",
"@target": "node15"
},
"edge15": {
"@source": "node14",
"@target": "node16"
}
},
"node17": {
"edge17": {
"@source": "node17",
"@target": "node18"
},
"edge20": {
"@source": "node17",
"@target": "node21"
}
},
"node18": {
"edge18": {
"@source": "node18",
"@target": "node19"
},
"edge19": {
"@source": "node18",
"@target": "node20"
}
},
"node21": {
"edge21": {
"@source": "node21",
"@target": "node22"
},
"edge28": {
"@source": "node21",
"@target": "node29"
}
},
"node22": {
"edge22": {
"@source": "node22",
"@target": "node23"
},
"edge25": {
"@source": "node22",
"@target": "node26"
}
},
"node23": {
"edge23": {
"@source": "node23",
"@target": "node24"
},
"edge24": {
"@source": "node23",
"@target": "node25"
}
},
"node26": {
"edge26": {
"@source": "node26",
"@target": "node27"
},
"edge27": {
"@source": "node26",
"@target": "node28"
}
},
"node29": {
"edge29": {
"@source": "node29",
"@target": "node30"
},
"edge46": {
"@source": "node29",
"@target": "node47"
}
},
"node3": {
"edge3": {
"@source": "node3",
"@target": "node4"
},
"edge6": {
"@source": "node3",
"@target": "node7"
}
},
"node30": {
"edge30": {
"@source": "node30",
"@target": "node31"
},
"edge33": {
"@source": "node30",
"@target": "node34"
}
},
"node31": {
"edge31": {
"@source": "node31",
"@target": "node32"
},
"edge32": {
"@source": "node31",
"@target": "node33"
}
},
"node34": {
"edge34": {
"@source": "node34",
"@target": "node35"
},
"edge39": {
"@source": "node34",
"@target": "node40"
}
},
"node35": {
"edge35": {
"@source": "node35",
"@target": "node36"
},
"edge36": {
"@source": "node35",
"@target": "node37"
}
},
"node37": {
"edge37": {
"@source": "node37",
"@target": "node38"
},
"edge38": {
"@source": "node37",
"@target": "node39"
}
},
"node4": {
"edge4": {
"@source": "node4",
"@target": "node5"
},
"edge5": {
"@source": "node4",
"@target": "node6"
}
},
"node40": {
"edge40": {
"@source": "node40",
"@target": "node41"
},
"edge43": {
"@source": "node40",
"@target": "node44"
}
},
"node41": {
"edge41": {
"@source": "node41",
"@target": "node42"
},
"edge42": {
"@source": "node41",
"@target": "node43"
}
},
"node44": {
"edge44": {
"@source": "node44",
"@target": "node45"
},
"edge45": {
"@source": "node44",
"@target": "node46"
}
},
"node47": {
"edge47": {
"@source": "node47",
"@target": "node48"
},
"edge48": {
"@source": "node47",
"@target": "node49"
}
},
"node49": {
"edge49": {
"@source": "node49",
"@target": "node50"
},
"edge52": {
"@source": "node49",
"@target": "node53"
}
},
"node50": {
"edge50": {
"@source": "node50",
"@target": "node51"
},
"edge51": {
"@source": "node50",
"@target": "node52"
}
},
"node53": {
"edge53": {
"@source": "node53",
"@target": "node54"
},
"edge54": {
"@source": "node53",
"@target": "node55"
}
},
"node55": {
"edge55": {
"@source": "node55",
"@target": "node56"
},
"edge56": {
"@source": "node55",
"@target": "node57"
}
},
"node57": {
"edge57": {
"@source": "node57",
"@target": "node58"
},
"edge58": {
"@source": "node57",
"@target": "node59"
}
},
"node59": {
"edge59": {
"@source": "node59",
"@target": "node60"
},
"edge60": {
"@source": "node59",
"@target": "node61"
}
},
"node61": {
"edge61": {
"@source": "node61",
"@target": "node62"
},
"edge62": {
"@source": "node61",
"@target": "node63"
}
},
"node7": {
"edge16": {
"@source": "node7",
"@target": "node17"
},
"edge7": {
"@source": "node7",
"@target": "node8"
}
},
"node8": {
"edge11": {
"@source": "node8",
"@target": "node12"
},
"edge8": {
"@source": "node8",
"@target": "node9"
}
},
"node9": {
"edge10": {
"@source": "node9",
"@target": "node11"
},
"edge9": {
"@source": "node9",
"@target": "node10"
}
}
},
"nodeById": {
"node1": {
"@root": true
},
"node10": {
"@otu": "otu4"
},
"node11": {
"@otu": "otu5"
},
"node12": {},
"node13": {
"@otu": "otu6"
},
"node14": {},
"node15": {
"@otu": "otu7"
},
"node16": {
"@otu": "otu8"
},
"node17": {},
"node18": {},
"node19": {
"@otu": "otu9"
},
"node2": {
"@otu": "otu1"
},
"node20": {
"@otu": "otu10"
},
"node21": {},
"node22": {},
"node23": {},
"node24": {
"@otu": "otu11"
},
"node25": {
"@otu": "otu12"
},
"node26": {},
"node27": {
"@otu": "otu13"
},
"node28": {
"@otu": "otu14"
},
"node29": {},
"node3": {},
"node30": {},
"node31": {},
"node32": {
"@otu": "otu15"
},
"node33": {
"@otu": "otu16"
},
"node34": {},
"node35": {},
"node36": {
"@otu": "otu17"
},
"node37": {},
"node38": {
"@otu": "otu18"
},
"node39": {
"@otu": "otu19"
},
"node4": {},
"node40": {},
"node41": {},
"node42": {
"@otu": "otu20"
},
"node43": {
"@otu": "otu21"
},
"node44": {},
"node45": {
"@otu": "otu22"
},
"node46": {
"@otu": "otu23"
},
"node47": {},
"node48": {
"@otu": "otu24"
},
"node49": {},
"node5": {
"@otu": "otu2"
},
"node50": {},
"node51": {
"@otu": "otu25"
},
"node52": {
"@otu": "otu26"
},
"node53": {},
"node54": {
"@otu": "otu27"
},
"node55": {},
"node56": {
"@otu": "otu28"
},
"node57": {},
"node58": {
"@otu": "otu29"
},
"node59": {},
"node6": {
"@otu": "otu3"
},
"node60": {
"@otu": "otu30"
},
"node61": {},
"node62": {
"@otu": "otu31"
},
"node63": {
"@otu": "otu32"
},
"node7": {},
"node8": {},
"node9": {}
}
}
}
}
}
}
}
